[{"point_timestamp":"2020-01-01","point_value":-0.0903451345},{"point_timestamp":"2020-01-02","point_value":0.0320710345},{"point_timestamp":"2020-01-03","point_value":0.2570226087},{"point_timestamp":"2020-01-04","point_value":0.433354595},{"point_timestamp":"2020-01-05","point_value":-0.0592966071},{"point_timestamp":"2020-01-06","point_value":0.1280208329},{"point_timestamp":"2020-01-07","point_value":0.0781761587},{"point_timestamp":"2020-01-08","point_value":-0.0887789377},{"point_timestamp":"2020-01-09","point_value":0.0336372313},{"point_timestamp":"2020-01-10","point_value":0.2585888055},{"point_timestamp":"2020-01-11","point_value":0.4349207918},{"point_timestamp":"2020-01-12","point_value":-0.0577304103},{"point_timestamp":"2020-01-13","point_value":0.1295870297},{"point_timestamp":"2020-01-14","point_value":0.0797423555},{"point_timestamp":"2020-01-15","point_value":-0.0872127409},{"point_timestamp":"2020-01-16","point_value":0.0352034281},{"point_timestamp":"2020-01-17","point_value":0.2601550023},{"point_timestamp":"2020-01-18","point_value":0.4364869886},{"point_timestamp":"2020-01-19","point_value":-0.0561642135},{"point_timestamp":"2020-01-20","point_value":0.1311532265},{"point_timestamp":"2020-01-21","point_value":0.0813085523},{"point_timestamp":"2020-01-22","point_value":-0.0856465441},{"point_timestamp":"2020-01-23","point_value":0.0367696249},{"point_timestamp":"2020-01-24","point_value":0.2617211991},{"point_timestamp":"2020-01-25","point_value":0.4380531854},{"point_timestamp":"2020-01-26","point_value":-0.0545980167},{"point_timestamp":"2020-01-27","point_value":0.1327194233},{"point_timestamp":"2020-01-28","point_value":0.0828747491},{"point_timestamp":"2020-01-29","point_value":-0.0840803473},{"point_timestamp":"2020-01-30","point_value":0.0383358217},{"point_timestamp":"2020-01-31","point_value":0.2632873959},{"point_timestamp":"2020-02-01","point_value":0.4396193822},{"point_timestamp":"2020-02-02","point_value":-0.0530318199},{"point_timestamp":"2020-02-03","point_value":0.1342856201},{"point_timestamp":"2020-02-04","point_value":0.0844409459},{"point_timestamp":"2020-02-05","point_value":-0.0825141505},{"point_timestamp":"2020-02-06","point_value":0.0399020185},{"point_timestamp":"2020-02-07","point_value":0.2648535927},{"point_timestamp":"2020-02-08","point_value":0.441185579},{"point_timestamp":"2020-02-09","point_value":-0.0514656231},{"point_timestamp":"2020-02-10","point_value":0.1358518169},{"point_timestamp":"2020-02-11","point_value":0.0860071427},{"point_timestamp":"2020-02-12","point_value":-0.0809479537},{"point_timestamp":"2020-02-13","point_value":0.0414682153},{"point_timestamp":"2020-02-14","point_value":0.2664197895},{"point_timestamp":"2020-02-15","point_value":0.4427517758},{"point_timestamp":"2020-02-16","point_value":-0.0498994263},{"point_timestamp":"2020-02-17","point_value":0.1374180137},{"point_timestamp":"2020-02-18","point_value":0.0875733395},{"point_timestamp":"2020-02-19","point_value":-0.0793817569},{"point_timestamp":"2020-02-20","point_value":0.0430344121},{"point_timestamp":"2020-02-21","point_value":0.2679859863},{"point_timestamp":"2020-02-22","point_value":0.4443179726},{"point_timestamp":"2020-02-23","point_value":-0.0483332295},{"point_timestamp":"2020-02-24","point_value":0.1389842105},{"point_timestamp":"2020-02-25","point_value":0.0891395363},{"point_timestamp":"2020-02-26","point_value":-0.0778155601},{"point_timestamp":"2020-02-27","point_value":0.0446006089},{"point_timestamp":"2020-02-28","point_value":0.2695521831},{"point_timestamp":"2020-02-29","point_value":0.4458841694},{"point_timestamp":"2020-03-01","point_value":-0.0467670327},{"point_timestamp":"2020-03-02","point_value":0.1405504073},{"point_timestamp":"2020-03-03","point_value":0.0907057331},{"point_timestamp":"2020-03-04","point_value":-0.0762493633},{"point_timestamp":"2020-03-05","point_value":0.0461668057},{"point_timestamp":"2020-03-06","point_value":0.2711183799},{"point_timestamp":"2020-03-07","point_value":0.4474503662},{"point_timestamp":"2020-03-08","point_value":-0.0452008359},{"point_timestamp":"2020-03-09","point_value":0.1421166041},{"point_timestamp":"2020-03-10","point_value":0.0922719299},{"point_timestamp":"2020-03-11","point_value":-0.0746831665},{"point_timestamp":"2020-03-12","point_value":0.0477330025},{"point_timestamp":"2020-03-13","point_value":0.2726845767},{"point_timestamp":"2020-03-14","point_value":0.449016563},{"point_timestamp":"2020-03-15","point_value":-0.0436346391},{"point_timestamp":"2020-03-16","point_value":0.1436828009},{"point_timestamp":"2020-03-17","point_value":0.0938381267},{"point_timestamp":"2020-03-18","point_value":-0.0731169697},{"point_timestamp":"2020-03-19","point_value":0.0492991993},{"point_timestamp":"2020-03-20","point_value":0.2742507735},{"point_timestamp":"2020-03-21","point_value":0.4505827598},{"point_timestamp":"2020-03-22","point_value":-0.0420684423},{"point_timestamp":"2020-03-23","point_value":0.1452489977},{"point_timestamp":"2020-03-24","point_value":0.0954043235},{"point_timestamp":"2020-03-25","point_value":-0.0715507729},{"point_timestamp":"2020-03-26","point_value":0.0508653961},{"point_timestamp":"2020-03-27","point_value":0.2758169703},{"point_timestamp":"2020-03-28","point_value":0.4521489566},{"point_timestamp":"2020-03-29","point_value":-0.0405022455},{"point_timestamp":"2020-03-30","point_value":0.1468151945},{"point_timestamp":"2020-03-31","point_value":0.0969705203},{"point_timestamp":"2020-04-01","point_value":-0.0699845761},{"point_timestamp":"2020-04-02","point_value":0.0524315929},{"point_timestamp":"2020-04-03","point_value":0.2773831671},{"point_timestamp":"2020-04-04","point_value":0.4537151534},{"point_timestamp":"2020-04-05","point_value":-0.0389360487},{"point_timestamp":"2020-04-06","point_value":0.1483813913},{"point_timestamp":"2020-04-07","point_value":0.0985367171},{"point_timestamp":"2020-04-08","point_value":-0.0684183793},{"point_timestamp":"2020-04-09","point_value":0.0539977897},{"point_timestamp":"2020-04-10","point_value":0.2789493639},{"point_timestamp":"2020-04-11","point_value":0.4552813502},{"point_timestamp":"2020-04-12","point_value":-0.0373698519},{"point_timestamp":"2020-04-13","point_value":0.1499475881},{"point_timestamp":"2020-04-14","point_value":0.1001029139},{"point_timestamp":"2020-04-15","point_value":-0.0668521826},{"point_timestamp":"2020-04-16","point_value":0.0555639865},{"point_timestamp":"2020-04-17","point_value":0.2805155607},{"point_timestamp":"2020-04-18","point_value":0.456847547},{"point_timestamp":"2020-04-19","point_value":-0.0358036551},{"point_timestamp":"2020-04-20","point_value":0.1515137849},{"point_timestamp":"2020-04-21","point_value":0.1016691107},{"point_timestamp":"2020-04-22","point_value":-0.0652859858},{"point_timestamp":"2020-04-23","point_value":0.0571301833},{"point_timestamp":"2020-04-24","point_value":0.2820817575},{"point_timestamp":"2020-04-25","point_value":0.4584137438},{"point_timestamp":"2020-04-26","point_value":-0.0342374583},{"point_timestamp":"2020-04-27","point_value":0.1530799817},{"point_timestamp":"2020-04-28","point_value":0.1032353075},{"point_timestamp":"2020-04-29","point_value":-0.063719789},{"point_timestamp":"2020-04-30","point_value":0.0586963801},{"point_timestamp":"2020-05-01","point_value":0.2836479543},{"point_timestamp":"2020-05-02","point_value":0.4599799406},{"point_timestamp":"2020-05-03","point_value":-0.0326712615},{"point_timestamp":"2020-05-04","point_value":0.1546461785},{"point_timestamp":"2020-05-05","point_value":0.1048015043},{"point_timestamp":"2020-05-06","point_value":-0.0621535922},{"point_timestamp":"2020-05-07","point_value":0.0602625769},{"point_timestamp":"2020-05-08","point_value":0.2852141511},{"point_timestamp":"2020-05-09","point_value":0.4615461374},{"point_timestamp":"2020-05-10","point_value":-0.0311050647},{"point_timestamp":"2020-05-11","point_value":0.1562123753},{"point_timestamp":"2020-05-12","point_value":0.1063677011},{"point_timestamp":"2020-05-13","point_value":-0.0605873954},{"point_timestamp":"2020-05-14","point_value":0.0618287737},{"point_timestamp":"2020-05-15","point_value":0.2867803479},{"point_timestamp":"2020-05-16","point_value":0.4631123342},{"point_timestamp":"2020-05-17","point_value":-0.0295388679},{"point_timestamp":"2020-05-18","point_value":0.1577785721},{"point_timestamp":"2020-05-19","point_value":0.1079338979},{"point_timestamp":"2020-05-20","point_value":-0.0590211986},{"point_timestamp":"2020-05-21","point_value":0.0633949705},{"point_timestamp":"2020-05-22","point_value":0.2883465447},{"point_timestamp":"2020-05-23","point_value":0.464678531},{"point_timestamp":"2020-05-24","point_value":-0.0279726711},{"point_timestamp":"2020-05-25","point_value":0.1593447689},{"point_timestamp":"2020-05-26","point_value":0.1095000947},{"point_timestamp":"2020-05-27","point_value":-0.0574550018},{"point_timestamp":"2020-05-28","point_value":0.0649611673},{"point_timestamp":"2020-05-29","point_value":0.2899127415},{"point_timestamp":"2020-05-30","point_value":0.4662447278},{"point_timestamp":"2020-05-31","point_value":-0.0264064743},{"point_timestamp":"2020-06-01","point_value":0.1609109657},{"point_timestamp":"2020-06-02","point_value":0.1110662915},{"point_timestamp":"2020-06-03","point_value":-0.055888805},{"point_timestamp":"2020-06-04","point_value":0.0665273641},{"point_timestamp":"2020-06-05","point_value":0.2914789383},{"point_timestamp":"2020-06-06","point_value":0.4678109246},{"point_timestamp":"2020-06-07","point_value":-0.0248402775},{"point_timestamp":"2020-06-08","point_value":0.1624771625},{"point_timestamp":"2020-06-09","point_value":0.1126324883},{"point_timestamp":"2020-06-10","point_value":-0.0543226082},{"point_timestamp":"2020-06-11","point_value":0.0680935609},{"point_timestamp":"2020-06-12","point_value":0.2930451351},{"point_timestamp":"2020-06-13","point_value":0.4693771214},{"point_timestamp":"2020-06-14","point_value":-0.0232740807},{"point_timestamp":"2020-06-15","point_value":0.1640433593},{"point_timestamp":"2020-06-16","point_value":0.114198685},{"point_timestamp":"2020-06-17","point_value":-0.0527564114},{"point_timestamp":"2020-06-18","point_value":0.0696597577},{"point_timestamp":"2020-06-19","point_value":0.2946113319},{"point_timestamp":"2020-06-20","point_value":0.4709433182},{"point_timestamp":"2020-06-21","point_value":-0.0217078839},{"point_timestamp":"2020-06-22","point_value":0.1656095561},{"point_timestamp":"2020-06-23","point_value":0.1157648818},{"point_timestamp":"2020-06-24","point_value":-0.0511902146},{"point_timestamp":"2020-06-25","point_value":0.0712259545},{"point_timestamp":"2020-06-26","point_value":0.2961775287},{"point_timestamp":"2020-06-27","point_value":0.472509515},{"point_timestamp":"2020-06-28","point_value":-0.0201416871},{"point_timestamp":"2020-06-29","point_value":0.1671757529},{"point_timestamp":"2020-06-30","point_value":0.1173310786},{"point_timestamp":"2020-07-01","point_value":-0.0496240178},{"point_timestamp":"2020-07-02","point_value":0.0727921513},{"point_timestamp":"2020-07-03","point_value":0.2977437255},{"point_timestamp":"2020-07-04","point_value":0.4740757118},{"point_timestamp":"2020-07-05","point_value":-0.0185754903},{"point_timestamp":"2020-07-06","point_value":0.1687419497},{"point_timestamp":"2020-07-07","point_value":0.1188972754},{"point_timestamp":"2020-07-08","point_value":-0.048057821},{"point_timestamp":"2020-07-09","point_value":0.0743583481},{"point_timestamp":"2020-07-10","point_value":0.2993099223},{"point_timestamp":"2020-07-11","point_value":0.4756419086},{"point_timestamp":"2020-07-12","point_value":-0.0170092935},{"point_timestamp":"2020-07-13","point_value":0.1703081465},{"point_timestamp":"2020-07-14","point_value":0.1204634722},{"point_timestamp":"2020-07-15","point_value":-0.0464916242},{"point_timestamp":"2020-07-16","point_value":0.0759245449},{"point_timestamp":"2020-07-17","point_value":0.3008761191},{"point_timestamp":"2020-07-18","point_value":0.4772081054},{"point_timestamp":"2020-07-19","point_value":-0.0154430967},{"point_timestamp":"2020-07-20","point_value":0.1718743433},{"point_timestamp":"2020-07-21","point_value":0.122029669},{"point_timestamp":"2020-07-22","point_value":-0.0449254274},{"point_timestamp":"2020-07-23","point_value":0.0774907417},{"point_timestamp":"2020-07-24","point_value":0.3024423159},{"point_timestamp":"2020-07-25","point_value":0.4787743022},{"point_timestamp":"2020-07-26","point_value":-0.0138768999},{"point_timestamp":"2020-07-27","point_value":0.1734405401},{"point_timestamp":"2020-07-28","point_value":0.1235958658},{"point_timestamp":"2020-07-29","point_value":-0.0433592306},{"point_timestamp":"2020-07-30","point_value":0.0790569385},{"point_timestamp":"2020-07-31","point_value":0.3040085127},{"point_timestamp":"2020-08-01","point_value":0.480340499},{"point_timestamp":"2020-08-02","point_value":-0.0123107031},{"point_timestamp":"2020-08-03","point_value":0.1750067369},{"point_timestamp":"2020-08-04","point_value":0.1251620626},{"point_timestamp":"2020-08-05","point_value":-0.0417930338},{"point_timestamp":"2020-08-06","point_value":0.0806231353},{"point_timestamp":"2020-08-07","point_value":0.3055747095},{"point_timestamp":"2020-08-08","point_value":0.4819066958},{"point_timestamp":"2020-08-09","point_value":-0.0107445063},{"point_timestamp":"2020-08-10","point_value":0.1765729337},{"point_timestamp":"2020-08-11","point_value":0.1267282594},{"point_timestamp":"2020-08-12","point_value":-0.040226837},{"point_timestamp":"2020-08-13","point_value":0.0821893321},{"point_timestamp":"2020-08-14","point_value":0.3071409063},{"point_timestamp":"2020-08-15","point_value":0.4834728926},{"point_timestamp":"2020-08-16","point_value":-0.0091783095},{"point_timestamp":"2020-08-17","point_value":0.1781391305},{"point_timestamp":"2020-08-18","point_value":0.1282944562},{"point_timestamp":"2020-08-19","point_value":-0.0386606402},{"point_timestamp":"2020-08-20","point_value":0.0837555289},{"point_timestamp":"2020-08-21","point_value":0.3087071031},{"point_timestamp":"2020-08-22","point_value":0.4850390894},{"point_timestamp":"2020-08-23","point_value":-0.0076121127},{"point_timestamp":"2020-08-24","point_value":0.1797053273},{"point_timestamp":"2020-08-25","point_value":0.129860653},{"point_timestamp":"2020-08-26","point_value":-0.0370944434},{"point_timestamp":"2020-08-27","point_value":0.0853217257},{"point_timestamp":"2020-08-28","point_value":0.3102732998},{"point_timestamp":"2020-08-29","point_value":0.4866052862},{"point_timestamp":"2020-08-30","point_value":-0.0060459159},{"point_timestamp":"2020-08-31","point_value":0.181271524},{"point_timestamp":"2020-09-01","point_value":0.1314268498},{"point_timestamp":"2020-09-02","point_value":-0.0355282466},{"point_timestamp":"2020-09-03","point_value":0.0868879225},{"point_timestamp":"2020-09-04","point_value":0.3118394966},{"point_timestamp":"2020-09-05","point_value":0.488171483},{"point_timestamp":"2020-09-06","point_value":-0.0044797191},{"point_timestamp":"2020-09-07","point_value":0.1828377208},{"point_timestamp":"2020-09-08","point_value":0.1329930466},{"point_timestamp":"2020-09-09","point_value":-0.0339620498},{"point_timestamp":"2020-09-10","point_value":0.0884541193},{"point_timestamp":"2020-09-11","point_value":0.3134056934},{"point_timestamp":"2020-09-12","point_value":0.4897376798},{"point_timestamp":"2020-09-13","point_value":-0.0029135223},{"point_timestamp":"2020-09-14","point_value":0.1844039176},{"point_timestamp":"2020-09-15","point_value":0.1345592434},{"point_timestamp":"2020-09-16","point_value":-0.032395853},{"point_timestamp":"2020-09-17","point_value":0.090020316},{"point_timestamp":"2020-09-18","point_value":0.3149718902},{"point_timestamp":"2020-09-19","point_value":0.4913038766},{"point_timestamp":"2020-09-20","point_value":-0.0013473256},{"point_timestamp":"2020-09-21","point_value":0.1859701144},{"point_timestamp":"2020-09-22","point_value":0.1361254402},{"point_timestamp":"2020-09-23","point_value":-0.0308296562},{"point_timestamp":"2020-09-24","point_value":0.0915865128},{"point_timestamp":"2020-09-25","point_value":0.316538087},{"point_timestamp":"2020-09-26","point_value":0.4928700734},{"point_timestamp":"2020-09-27","point_value":0.0002188712},{"point_timestamp":"2020-09-28","point_value":0.1875363112},{"point_timestamp":"2020-09-29","point_value":0.137691637},{"point_timestamp":"2020-09-30","point_value":-0.0292634594},{"point_timestamp":"2020-10-01","point_value":0.0931527096},{"point_timestamp":"2020-10-02","point_value":0.3181042838},{"point_timestamp":"2020-10-03","point_value":0.4944362702},{"point_timestamp":"2020-10-04","point_value":0.001785068},{"point_timestamp":"2020-10-05","point_value":0.189102508},{"point_timestamp":"2020-10-06","point_value":0.1392578338},{"point_timestamp":"2020-10-07","point_value":-0.0276972626},{"point_timestamp":"2020-10-08","point_value":0.0947189064},{"point_timestamp":"2020-10-09","point_value":0.3196704806},{"point_timestamp":"2020-10-10","point_value":0.496002467},{"point_timestamp":"2020-10-11","point_value":0.0033512648},{"point_timestamp":"2020-10-12","point_value":0.1906687048},{"point_timestamp":"2020-10-13","point_value":0.1408240306},{"point_timestamp":"2020-10-14","point_value":-0.0261310658},{"point_timestamp":"2020-10-15","point_value":0.0962851032},{"point_timestamp":"2020-10-16","point_value":0.3212366774},{"point_timestamp":"2020-10-17","point_value":0.4975686638},{"point_timestamp":"2020-10-18","point_value":0.0049174616},{"point_timestamp":"2020-10-19","point_value":0.1922349016},{"point_timestamp":"2020-10-20","point_value":0.1423902274},{"point_timestamp":"2020-10-21","point_value":-0.024564869},{"point_timestamp":"2020-10-22","point_value":0.0978513},{"point_timestamp":"2020-10-23","point_value":0.3228028742},{"point_timestamp":"2020-10-24","point_value":0.4991348606},{"point_timestamp":"2020-10-25","point_value":0.0064836584},{"point_timestamp":"2020-10-26","point_value":0.1938010984},{"point_timestamp":"2020-10-27","point_value":0.1439564242},{"point_timestamp":"2020-10-28","point_value":-0.0229986722},{"point_timestamp":"2020-10-29","point_value":0.0994174968},{"point_timestamp":"2020-10-30","point_value":0.324369071},{"point_timestamp":"2020-10-31","point_value":0.5007010574},{"point_timestamp":"2020-11-01","point_value":0.0080498552},{"point_timestamp":"2020-11-02","point_value":0.1953672952},{"point_timestamp":"2020-11-03","point_value":0.145522621},{"point_timestamp":"2020-11-04","point_value":-0.0214324754},{"point_timestamp":"2020-11-05","point_value":0.1009836936},{"point_timestamp":"2020-11-06","point_value":0.3259352678},{"point_timestamp":"2020-11-07","point_value":0.5022672542},{"point_timestamp":"2020-11-08","point_value":0.009616052},{"point_timestamp":"2020-11-09","point_value":0.196933492},{"point_timestamp":"2020-11-10","point_value":0.1470888178},{"point_timestamp":"2020-11-11","point_value":-0.0198662786},{"point_timestamp":"2020-11-12","point_value":0.1025498904},{"point_timestamp":"2020-11-13","point_value":0.3275014646},{"point_timestamp":"2020-11-14","point_value":0.503833451},{"point_timestamp":"2020-11-15","point_value":0.0111822488},{"point_timestamp":"2020-11-16","point_value":0.1984996888},{"point_timestamp":"2020-11-17","point_value":0.1486550146},{"point_timestamp":"2020-11-18","point_value":-0.0183000818},{"point_timestamp":"2020-11-19","point_value":0.1041160872},{"point_timestamp":"2020-11-20","point_value":0.3290676614},{"point_timestamp":"2020-11-21","point_value":0.5053996478},{"point_timestamp":"2020-11-22","point_value":0.0127484456},{"point_timestamp":"2020-11-23","point_value":0.2000658856},{"point_timestamp":"2020-11-24","point_value":0.1502212114},{"point_timestamp":"2020-11-25","point_value":-0.016733885},{"point_timestamp":"2020-11-26","point_value":0.105682284},{"point_timestamp":"2020-11-27","point_value":0.3306338582},{"point_timestamp":"2020-11-28","point_value":0.5069658446},{"point_timestamp":"2020-11-29","point_value":0.0143146424},{"point_timestamp":"2020-11-30","point_value":0.2016320824},{"point_timestamp":"2020-12-01","point_value":0.1517874082},{"point_timestamp":"2020-12-02","point_value":-0.0151676882},{"point_timestamp":"2020-12-03","point_value":0.1072484808},{"point_timestamp":"2020-12-04","point_value":0.332200055},{"point_timestamp":"2020-12-05","point_value":0.5085320414},{"point_timestamp":"2020-12-06","point_value":0.0158808392},{"point_timestamp":"2020-12-07","point_value":0.2031982792},{"point_timestamp":"2020-12-08","point_value":0.153353605},{"point_timestamp":"2020-12-09","point_value":-0.0136014914},{"point_timestamp":"2020-12-10","point_value":0.1088146776},{"point_timestamp":"2020-12-11","point_value":0.3337662518},{"point_timestamp":"2020-12-12","point_value":0.5100982382},{"point_timestamp":"2020-12-13","point_value":0.017447036},{"point_timestamp":"2020-12-14","point_value":0.204764476},{"point_timestamp":"2020-12-15","point_value":0.1549198018},{"point_timestamp":"2020-12-16","point_value":-0.0120352946},{"point_timestamp":"2020-12-17","point_value":0.1103808744},{"point_timestamp":"2020-12-18","point_value":0.3353324486},{"point_timestamp":"2020-12-19","point_value":0.5116644349},{"point_timestamp":"2020-12-20","point_value":0.0190132328},{"point_timestamp":"2020-12-21","point_value":0.2063306728},{"point_timestamp":"2020-12-22","point_value":0.1564859986},{"point_timestamp":"2020-12-23","point_value":-0.0104690978},{"point_timestamp":"2020-12-24","point_value":0.1119470712},{"point_timestamp":"2020-12-25","point_value":0.3368986454},{"point_timestamp":"2020-12-26","point_value":0.5132306317},{"point_timestamp":"2020-12-27","point_value":0.0205794296},{"point_timestamp":"2020-12-28","point_value":0.2078968696},{"point_timestamp":"2020-12-29","point_value":0.1580521954},{"point_timestamp":"2020-12-30","point_value":-0.008902901},{"point_timestamp":"2020-12-31","point_value":0.113513268},{"point_timestamp":"2021-01-01","point_value":0.3384648422},{"point_timestamp":"2021-01-02","point_value":0.5147968285},{"point_timestamp":"2021-01-03","point_value":0.0221456264},{"point_timestamp":"2021-01-04","point_value":0.2094630664},{"point_timestamp":"2021-01-05","point_value":0.1596183922},{"point_timestamp":"2021-01-06","point_value":-0.0073367042},{"point_timestamp":"2021-01-07","point_value":0.1150794648},{"point_timestamp":"2021-01-08","point_value":0.340031039},{"point_timestamp":"2021-01-09","point_value":0.5163630253},{"point_timestamp":"2021-01-10","point_value":0.0237118232},{"point_timestamp":"2021-01-11","point_value":0.2110292632},{"point_timestamp":"2021-01-12","point_value":0.161184589},{"point_timestamp":"2021-01-13","point_value":-0.0057705074},{"point_timestamp":"2021-01-14","point_value":0.1166456616},{"point_timestamp":"2021-01-15","point_value":0.3415972358},{"point_timestamp":"2021-01-16","point_value":0.5179292221},{"point_timestamp":"2021-01-17","point_value":0.02527802},{"point_timestamp":"2021-01-18","point_value":0.21259546},{"point_timestamp":"2021-01-19","point_value":0.1627507858},{"point_timestamp":"2021-01-20","point_value":-0.0042043106},{"point_timestamp":"2021-01-21","point_value":0.1182118584},{"point_timestamp":"2021-01-22","point_value":0.3431634326},{"point_timestamp":"2021-01-23","point_value":0.5194954189},{"point_timestamp":"2021-01-24","point_value":0.0268442168},{"point_timestamp":"2021-01-25","point_value":0.2141616568},{"point_timestamp":"2021-01-26","point_value":0.1643169826},{"point_timestamp":"2021-01-27","point_value":-0.0026381138},{"point_timestamp":"2021-01-28","point_value":0.1197780552},{"point_timestamp":"2021-01-29","point_value":0.3447296294},{"point_timestamp":"2021-01-30","point_value":0.5210616157},{"point_timestamp":"2021-01-31","point_value":0.0284104136},{"point_timestamp":"2021-02-01","point_value":0.2157278536},{"point_timestamp":"2021-02-02","point_value":0.1658831794},{"point_timestamp":"2021-02-03","point_value":-0.001071917},{"point_timestamp":"2021-02-04","point_value":0.121344252},{"point_timestamp":"2021-02-05","point_value":0.3462958262},{"point_timestamp":"2021-02-06","point_value":0.5226278125},{"point_timestamp":"2021-02-07","point_value":0.0299766104},{"point_timestamp":"2021-02-08","point_value":0.2172940504},{"point_timestamp":"2021-02-09","point_value":0.1674493762},{"point_timestamp":"2021-02-10","point_value":0.0004942798},{"point_timestamp":"2021-02-11","point_value":0.1229104488},{"point_timestamp":"2021-02-12","point_value":0.347862023},{"point_timestamp":"2021-02-13","point_value":0.5241940093},{"point_timestamp":"2021-02-14","point_value":0.0315428072},{"point_timestamp":"2021-02-15","point_value":0.2188602472},{"point_timestamp":"2021-02-16","point_value":0.169015573},{"point_timestamp":"2021-02-17","point_value":0.0020604766},{"point_timestamp":"2021-02-18","point_value":0.1244766456},{"point_timestamp":"2021-02-19","point_value":0.3494282198},{"point_timestamp":"2021-02-20","point_value":0.5257602061},{"point_timestamp":"2021-02-21","point_value":0.033109004},{"point_timestamp":"2021-02-22","point_value":0.220426444},{"point_timestamp":"2021-02-23","point_value":0.1705817698},{"point_timestamp":"2021-02-24","point_value":0.0036266734},{"point_timestamp":"2021-02-25","point_value":0.1260428424},{"point_timestamp":"2021-02-26","point_value":0.3509944166},{"point_timestamp":"2021-02-27","point_value":0.5273264029},{"point_timestamp":"2021-02-28","point_value":0.0346752008},{"point_timestamp":"2021-03-01","point_value":0.2219926408},{"point_timestamp":"2021-03-02","point_value":0.1721479666},{"point_timestamp":"2021-03-03","point_value":0.0051928702},{"point_timestamp":"2021-03-04","point_value":0.1276090392},{"point_timestamp":"2021-03-05","point_value":0.3525606134},{"point_timestamp":"2021-03-06","point_value":0.5288925997},{"point_timestamp":"2021-03-07","point_value":0.0362413976},{"point_timestamp":"2021-03-08","point_value":0.2235588376},{"point_timestamp":"2021-03-09","point_value":0.1737141634},{"point_timestamp":"2021-03-10","point_value":0.006759067},{"point_timestamp":"2021-03-11","point_value":0.129175236},{"point_timestamp":"2021-03-12","point_value":0.3541268102},{"point_timestamp":"2021-03-13","point_value":0.5304587965},{"point_timestamp":"2021-03-14","point_value":0.0378075944},{"point_timestamp":"2021-03-15","point_value":0.2251250344},{"point_timestamp":"2021-03-16","point_value":0.1752803602},{"point_timestamp":"2021-03-17","point_value":0.0083252638},{"point_timestamp":"2021-03-18","point_value":0.1307414328},{"point_timestamp":"2021-03-19","point_value":0.355693007},{"point_timestamp":"2021-03-20","point_value":0.5320249933},{"point_timestamp":"2021-03-21","point_value":0.0393737912},{"point_timestamp":"2021-03-22","point_value":0.2266912312},{"point_timestamp":"2021-03-23","point_value":0.176846557},{"point_timestamp":"2021-03-24","point_value":0.0098914606},{"point_timestamp":"2021-03-25","point_value":0.1323076296},{"point_timestamp":"2021-03-26","point_value":0.3572592038},{"point_timestamp":"2021-03-27","point_value":0.5335911901},{"point_timestamp":"2021-03-28","point_value":0.040939988},{"point_timestamp":"2021-03-29","point_value":0.228257428},{"point_timestamp":"2021-03-30","point_value":0.1784127538},{"point_timestamp":"2021-03-31","point_value":0.0114576574},{"point_timestamp":"2021-04-01","point_value":0.1338738264},{"point_timestamp":"2021-04-02","point_value":0.3588254006},{"point_timestamp":"2021-04-03","point_value":0.5351573869},{"point_timestamp":"2021-04-04","point_value":0.0425061848},{"point_timestamp":"2021-04-05","point_value":0.2298236248},{"point_timestamp":"2021-04-06","point_value":0.1799789506},{"point_timestamp":"2021-04-07","point_value":0.0130238542},{"point_timestamp":"2021-04-08","point_value":0.1354400232},{"point_timestamp":"2021-04-09","point_value":0.3603915974},{"point_timestamp":"2021-04-10","point_value":0.5367235837},{"point_timestamp":"2021-04-11","point_value":0.0440723816},{"point_timestamp":"2021-04-12","point_value":0.2313898216},{"point_timestamp":"2021-04-13","point_value":0.1815451474},{"point_timestamp":"2021-04-14","point_value":0.0145900509},{"point_timestamp":"2021-04-15","point_value":0.13700622},{"point_timestamp":"2021-04-16","point_value":0.3619577942},{"point_timestamp":"2021-04-17","point_value":0.5382897805},{"point_timestamp":"2021-04-18","point_value":0.0456385784},{"point_timestamp":"2021-04-19","point_value":0.2329560184},{"point_timestamp":"2021-04-20","point_value":0.1831113442},{"point_timestamp":"2021-04-21","point_value":0.0161562477},{"point_timestamp":"2021-04-22","point_value":0.1385724168},{"point_timestamp":"2021-04-23","point_value":0.363523991},{"point_timestamp":"2021-04-24","point_value":0.5398559773},{"point_timestamp":"2021-04-25","point_value":0.0472047752},{"point_timestamp":"2021-04-26","point_value":0.2345222152},{"point_timestamp":"2021-04-27","point_value":0.184677541},{"point_timestamp":"2021-04-28","point_value":0.0177224445},{"point_timestamp":"2021-04-29","point_value":0.1401386136},{"point_timestamp":"2021-04-30","point_value":0.3650901878},{"point_timestamp":"2021-05-01","point_value":0.5414221741},{"point_timestamp":"2021-05-02","point_value":0.048770972},{"point_timestamp":"2021-05-03","point_value":0.236088412},{"point_timestamp":"2021-05-04","point_value":0.1862437378},{"point_timestamp":"2021-05-05","point_value":0.0192886413},{"point_timestamp":"2021-05-06","point_value":0.1417048104},{"point_timestamp":"2021-05-07","point_value":0.3666563846},{"point_timestamp":"2021-05-08","point_value":0.5429883709},{"point_timestamp":"2021-05-09","point_value":0.0503371688},{"point_timestamp":"2021-05-10","point_value":0.2376546088},{"point_timestamp":"2021-05-11","point_value":0.1878099346},{"point_timestamp":"2021-05-12","point_value":0.0208548381},{"point_timestamp":"2021-05-13","point_value":0.1432710072},{"point_timestamp":"2021-05-14","point_value":0.3682225814}]