[{"point_timestamp":"2020-01-01","point_value":0.0052946849},{"point_timestamp":"2020-01-02","point_value":0.088159782},{"point_timestamp":"2020-01-03","point_value":0.1525798189},{"point_timestamp":"2020-01-04","point_value":-0.0991898191},{"point_timestamp":"2020-01-05","point_value":0.0009142009},{"point_timestamp":"2020-01-06","point_value":-0.1206487061},{"point_timestamp":"2020-01-07","point_value":-0.0056420447},{"point_timestamp":"2020-01-08","point_value":0.0049052072},{"point_timestamp":"2020-01-09","point_value":0.0877703044},{"point_timestamp":"2020-01-10","point_value":0.1521903413},{"point_timestamp":"2020-01-11","point_value":-0.0995792967},{"point_timestamp":"2020-01-12","point_value":0.0005247232},{"point_timestamp":"2020-01-13","point_value":-0.1210381838},{"point_timestamp":"2020-01-14","point_value":-0.0060315223},{"point_timestamp":"2020-01-15","point_value":0.0045157296},{"point_timestamp":"2020-01-16","point_value":0.0873808267},{"point_timestamp":"2020-01-17","point_value":0.1518008636},{"point_timestamp":"2020-01-18","point_value":-0.0999687744},{"point_timestamp":"2020-01-19","point_value":0.0001352456},{"point_timestamp":"2020-01-20","point_value":-0.1214276614},{"point_timestamp":"2020-01-21","point_value":-0.006421},{"point_timestamp":"2020-01-22","point_value":0.0041262519},{"point_timestamp":"2020-01-23","point_value":0.086991349},{"point_timestamp":"2020-01-24","point_value":0.1514113859},{"point_timestamp":"2020-01-25","point_value":-0.1003582521},{"point_timestamp":"2020-01-26","point_value":-0.0002542321},{"point_timestamp":"2020-01-27","point_value":-0.1218171391},{"point_timestamp":"2020-01-28","point_value":-0.0068104776},{"point_timestamp":"2020-01-29","point_value":0.0037367743},{"point_timestamp":"2020-01-30","point_value":0.0866018714},{"point_timestamp":"2020-01-31","point_value":0.1510219083},{"point_timestamp":"2020-02-01","point_value":-0.1007477297},{"point_timestamp":"2020-02-02","point_value":-0.0006437097},{"point_timestamp":"2020-02-03","point_value":-0.1222066168},{"point_timestamp":"2020-02-04","point_value":-0.0071999553},{"point_timestamp":"2020-02-05","point_value":0.0033472966},{"point_timestamp":"2020-02-06","point_value":0.0862123937},{"point_timestamp":"2020-02-07","point_value":0.1506324306},{"point_timestamp":"2020-02-08","point_value":-0.1011372074},{"point_timestamp":"2020-02-09","point_value":-0.0010331874},{"point_timestamp":"2020-02-10","point_value":-0.1225960944},{"point_timestamp":"2020-02-11","point_value":-0.007589433},{"point_timestamp":"2020-02-12","point_value":0.0029578189},{"point_timestamp":"2020-02-13","point_value":0.0858229161},{"point_timestamp":"2020-02-14","point_value":0.150242953},{"point_timestamp":"2020-02-15","point_value":-0.101526685},{"point_timestamp":"2020-02-16","point_value":-0.0014226651},{"point_timestamp":"2020-02-17","point_value":-0.1229855721},{"point_timestamp":"2020-02-18","point_value":-0.0079789106},{"point_timestamp":"2020-02-19","point_value":0.0025683413},{"point_timestamp":"2020-02-20","point_value":0.0854334384},{"point_timestamp":"2020-02-21","point_value":0.1498534753},{"point_timestamp":"2020-02-22","point_value":-0.1019161627},{"point_timestamp":"2020-02-23","point_value":-0.0018121427},{"point_timestamp":"2020-02-24","point_value":-0.1233750497},{"point_timestamp":"2020-02-25","point_value":-0.0083683883},{"point_timestamp":"2020-02-26","point_value":0.0021788636},{"point_timestamp":"2020-02-27","point_value":0.0850439608},{"point_timestamp":"2020-02-28","point_value":0.1494639977},{"point_timestamp":"2020-02-29","point_value":-0.1023056403},{"point_timestamp":"2020-03-01","point_value":-0.0022016204},{"point_timestamp":"2020-03-02","point_value":-0.1237645274},{"point_timestamp":"2020-03-03","point_value":-0.0087578659},{"point_timestamp":"2020-03-04","point_value":0.001789386},{"point_timestamp":"2020-03-05","point_value":0.0846544831},{"point_timestamp":"2020-03-06","point_value":0.14907452},{"point_timestamp":"2020-03-07","point_value":-0.102695118},{"point_timestamp":"2020-03-08","point_value":-0.002591098},{"point_timestamp":"2020-03-09","point_value":-0.124154005},{"point_timestamp":"2020-03-10","point_value":-0.0091473436},{"point_timestamp":"2020-03-11","point_value":0.0013999083},{"point_timestamp":"2020-03-12","point_value":0.0842650054},{"point_timestamp":"2020-03-13","point_value":0.1486850423},{"point_timestamp":"2020-03-14","point_value":-0.1030845957},{"point_timestamp":"2020-03-15","point_value":-0.0029805757},{"point_timestamp":"2020-03-16","point_value":-0.1245434827},{"point_timestamp":"2020-03-17","point_value":-0.0095368212},{"point_timestamp":"2020-03-18","point_value":0.0010104307},{"point_timestamp":"2020-03-19","point_value":0.0838755278},{"point_timestamp":"2020-03-20","point_value":0.1482955647},{"point_timestamp":"2020-03-21","point_value":-0.1034740733},{"point_timestamp":"2020-03-22","point_value":-0.0033700533},{"point_timestamp":"2020-03-23","point_value":-0.1249329604},{"point_timestamp":"2020-03-24","point_value":-0.0099262989},{"point_timestamp":"2020-03-25","point_value":0.000620953},{"point_timestamp":"2020-03-26","point_value":0.0834860501},{"point_timestamp":"2020-03-27","point_value":0.147906087},{"point_timestamp":"2020-03-28","point_value":-0.103863551},{"point_timestamp":"2020-03-29","point_value":-0.003759531},{"point_timestamp":"2020-03-30","point_value":-0.125322438},{"point_timestamp":"2020-03-31","point_value":-0.0103157766},{"point_timestamp":"2020-04-01","point_value":0.0002314753},{"point_timestamp":"2020-04-02","point_value":0.0830965725},{"point_timestamp":"2020-04-03","point_value":0.1475166094},{"point_timestamp":"2020-04-04","point_value":-0.1042530286},{"point_timestamp":"2020-04-05","point_value":-0.0041490086},{"point_timestamp":"2020-04-06","point_value":-0.1257119157},{"point_timestamp":"2020-04-07","point_value":-0.0107052542},{"point_timestamp":"2020-04-08","point_value":-0.0001580023},{"point_timestamp":"2020-04-09","point_value":0.0827070948},{"point_timestamp":"2020-04-10","point_value":0.1471271317},{"point_timestamp":"2020-04-11","point_value":-0.1046425063},{"point_timestamp":"2020-04-12","point_value":-0.0045384863},{"point_timestamp":"2020-04-13","point_value":-0.1261013933},{"point_timestamp":"2020-04-14","point_value":-0.0110947319},{"point_timestamp":"2020-04-15","point_value":-0.00054748},{"point_timestamp":"2020-04-16","point_value":0.0823176172},{"point_timestamp":"2020-04-17","point_value":0.1467376541},{"point_timestamp":"2020-04-18","point_value":-0.1050319839},{"point_timestamp":"2020-04-19","point_value":-0.004927964},{"point_timestamp":"2020-04-20","point_value":-0.126490871},{"point_timestamp":"2020-04-21","point_value":-0.0114842095},{"point_timestamp":"2020-04-22","point_value":-0.0009369576},{"point_timestamp":"2020-04-23","point_value":0.0819281395},{"point_timestamp":"2020-04-24","point_value":0.1463481764},{"point_timestamp":"2020-04-25","point_value":-0.1054214616},{"point_timestamp":"2020-04-26","point_value":-0.0053174416},{"point_timestamp":"2020-04-27","point_value":-0.1268803486},{"point_timestamp":"2020-04-28","point_value":-0.0118736872},{"point_timestamp":"2020-04-29","point_value":-0.0013264353},{"point_timestamp":"2020-04-30","point_value":0.0815386618},{"point_timestamp":"2020-05-01","point_value":0.1459586987},{"point_timestamp":"2020-05-02","point_value":-0.1058109393},{"point_timestamp":"2020-05-03","point_value":-0.0057069193},{"point_timestamp":"2020-05-04","point_value":-0.1272698263},{"point_timestamp":"2020-05-05","point_value":-0.0122631648},{"point_timestamp":"2020-05-06","point_value":-0.0017159129},{"point_timestamp":"2020-05-07","point_value":0.0811491842},{"point_timestamp":"2020-05-08","point_value":0.1455692211},{"point_timestamp":"2020-05-09","point_value":-0.1062004169},{"point_timestamp":"2020-05-10","point_value":-0.0060963969},{"point_timestamp":"2020-05-11","point_value":-0.127659304},{"point_timestamp":"2020-05-12","point_value":-0.0126526425},{"point_timestamp":"2020-05-13","point_value":-0.0021053906},{"point_timestamp":"2020-05-14","point_value":0.0807597065},{"point_timestamp":"2020-05-15","point_value":0.1451797434},{"point_timestamp":"2020-05-16","point_value":-0.1065898946},{"point_timestamp":"2020-05-17","point_value":-0.0064858746},{"point_timestamp":"2020-05-18","point_value":-0.1280487816},{"point_timestamp":"2020-05-19","point_value":-0.0130421202},{"point_timestamp":"2020-05-20","point_value":-0.0024948683},{"point_timestamp":"2020-05-21","point_value":0.0803702289},{"point_timestamp":"2020-05-22","point_value":0.1447902658},{"point_timestamp":"2020-05-23","point_value":-0.1069793722},{"point_timestamp":"2020-05-24","point_value":-0.0068753522},{"point_timestamp":"2020-05-25","point_value":-0.1284382593},{"point_timestamp":"2020-05-26","point_value":-0.0134315978},{"point_timestamp":"2020-05-27","point_value":-0.0028843459},{"point_timestamp":"2020-05-28","point_value":0.0799807512},{"point_timestamp":"2020-05-29","point_value":0.1444007881},{"point_timestamp":"2020-05-30","point_value":-0.1073688499},{"point_timestamp":"2020-05-31","point_value":-0.0072648299},{"point_timestamp":"2020-06-01","point_value":-0.1288277369},{"point_timestamp":"2020-06-02","point_value":-0.0138210755},{"point_timestamp":"2020-06-03","point_value":-0.0032738236},{"point_timestamp":"2020-06-04","point_value":0.0795912736},{"point_timestamp":"2020-06-05","point_value":0.1440113105},{"point_timestamp":"2020-06-06","point_value":-0.1077583275},{"point_timestamp":"2020-06-07","point_value":-0.0076543076},{"point_timestamp":"2020-06-08","point_value":-0.1292172146},{"point_timestamp":"2020-06-09","point_value":-0.0142105531},{"point_timestamp":"2020-06-10","point_value":-0.0036633012},{"point_timestamp":"2020-06-11","point_value":0.0792017959},{"point_timestamp":"2020-06-12","point_value":0.1436218328},{"point_timestamp":"2020-06-13","point_value":-0.1081478052},{"point_timestamp":"2020-06-14","point_value":-0.0080437852},{"point_timestamp":"2020-06-15","point_value":-0.1296066922},{"point_timestamp":"2020-06-16","point_value":-0.0146000308},{"point_timestamp":"2020-06-17","point_value":-0.0040527789},{"point_timestamp":"2020-06-18","point_value":0.0788123183},{"point_timestamp":"2020-06-19","point_value":0.1432323551},{"point_timestamp":"2020-06-20","point_value":-0.1085372829},{"point_timestamp":"2020-06-21","point_value":-0.0084332629},{"point_timestamp":"2020-06-22","point_value":-0.1299961699},{"point_timestamp":"2020-06-23","point_value":-0.0149895084},{"point_timestamp":"2020-06-24","point_value":-0.0044422565},{"point_timestamp":"2020-06-25","point_value":0.0784228406},{"point_timestamp":"2020-06-26","point_value":0.1428428775},{"point_timestamp":"2020-06-27","point_value":-0.1089267605},{"point_timestamp":"2020-06-28","point_value":-0.0088227405},{"point_timestamp":"2020-06-29","point_value":-0.1303856476},{"point_timestamp":"2020-06-30","point_value":-0.0153789861},{"point_timestamp":"2020-07-01","point_value":-0.0048317342},{"point_timestamp":"2020-07-02","point_value":0.0780333629},{"point_timestamp":"2020-07-03","point_value":0.1424533998},{"point_timestamp":"2020-07-04","point_value":-0.1093162382},{"point_timestamp":"2020-07-05","point_value":-0.0092122182},{"point_timestamp":"2020-07-06","point_value":-0.1307751252},{"point_timestamp":"2020-07-07","point_value":-0.0157684638},{"point_timestamp":"2020-07-08","point_value":-0.0052212119},{"point_timestamp":"2020-07-09","point_value":0.0776438853},{"point_timestamp":"2020-07-10","point_value":0.1420639222},{"point_timestamp":"2020-07-11","point_value":-0.1097057158},{"point_timestamp":"2020-07-12","point_value":-0.0096016958},{"point_timestamp":"2020-07-13","point_value":-0.1311646029},{"point_timestamp":"2020-07-14","point_value":-0.0161579414},{"point_timestamp":"2020-07-15","point_value":-0.0056106895},{"point_timestamp":"2020-07-16","point_value":0.0772544076},{"point_timestamp":"2020-07-17","point_value":0.1416744445},{"point_timestamp":"2020-07-18","point_value":-0.1100951935},{"point_timestamp":"2020-07-19","point_value":-0.0099911735},{"point_timestamp":"2020-07-20","point_value":-0.1315540805},{"point_timestamp":"2020-07-21","point_value":-0.0165474191},{"point_timestamp":"2020-07-22","point_value":-0.0060001672},{"point_timestamp":"2020-07-23","point_value":0.07686493},{"point_timestamp":"2020-07-24","point_value":0.1412849669},{"point_timestamp":"2020-07-25","point_value":-0.1104846711},{"point_timestamp":"2020-07-26","point_value":-0.0103806512},{"point_timestamp":"2020-07-27","point_value":-0.1319435582},{"point_timestamp":"2020-07-28","point_value":-0.0169368967},{"point_timestamp":"2020-07-29","point_value":-0.0063896448},{"point_timestamp":"2020-07-30","point_value":0.0764754523},{"point_timestamp":"2020-07-31","point_value":0.1408954892},{"point_timestamp":"2020-08-01","point_value":-0.1108741488},{"point_timestamp":"2020-08-02","point_value":-0.0107701288},{"point_timestamp":"2020-08-03","point_value":-0.1323330358},{"point_timestamp":"2020-08-04","point_value":-0.0173263744},{"point_timestamp":"2020-08-05","point_value":-0.0067791225},{"point_timestamp":"2020-08-06","point_value":0.0760859747},{"point_timestamp":"2020-08-07","point_value":0.1405060115},{"point_timestamp":"2020-08-08","point_value":-0.1112636265},{"point_timestamp":"2020-08-09","point_value":-0.0111596065},{"point_timestamp":"2020-08-10","point_value":-0.1327225135},{"point_timestamp":"2020-08-11","point_value":-0.017715852},{"point_timestamp":"2020-08-12","point_value":-0.0071686001},{"point_timestamp":"2020-08-13","point_value":0.075696497},{"point_timestamp":"2020-08-14","point_value":0.1401165339},{"point_timestamp":"2020-08-15","point_value":-0.1116531041},{"point_timestamp":"2020-08-16","point_value":-0.0115490841},{"point_timestamp":"2020-08-17","point_value":-0.1331119912},{"point_timestamp":"2020-08-18","point_value":-0.0181053297},{"point_timestamp":"2020-08-19","point_value":-0.0075580778},{"point_timestamp":"2020-08-20","point_value":0.0753070193},{"point_timestamp":"2020-08-21","point_value":0.1397270562},{"point_timestamp":"2020-08-22","point_value":-0.1120425818},{"point_timestamp":"2020-08-23","point_value":-0.0119385618},{"point_timestamp":"2020-08-24","point_value":-0.1335014688},{"point_timestamp":"2020-08-25","point_value":-0.0184948074},{"point_timestamp":"2020-08-26","point_value":-0.0079475555},{"point_timestamp":"2020-08-27","point_value":0.0749175417},{"point_timestamp":"2020-08-28","point_value":0.1393375786},{"point_timestamp":"2020-08-29","point_value":-0.1124320594},{"point_timestamp":"2020-08-30","point_value":-0.0123280394},{"point_timestamp":"2020-08-31","point_value":-0.1338909465},{"point_timestamp":"2020-09-01","point_value":-0.018884285},{"point_timestamp":"2020-09-02","point_value":-0.0083370331},{"point_timestamp":"2020-09-03","point_value":0.074528064},{"point_timestamp":"2020-09-04","point_value":0.1389481009},{"point_timestamp":"2020-09-05","point_value":-0.1128215371},{"point_timestamp":"2020-09-06","point_value":-0.0127175171},{"point_timestamp":"2020-09-07","point_value":-0.1342804241},{"point_timestamp":"2020-09-08","point_value":-0.0192737627},{"point_timestamp":"2020-09-09","point_value":-0.0087265108},{"point_timestamp":"2020-09-10","point_value":0.0741385864},{"point_timestamp":"2020-09-11","point_value":0.1385586233},{"point_timestamp":"2020-09-12","point_value":-0.1132110147},{"point_timestamp":"2020-09-13","point_value":-0.0131069948},{"point_timestamp":"2020-09-14","point_value":-0.1346699018},{"point_timestamp":"2020-09-15","point_value":-0.0196632403},{"point_timestamp":"2020-09-16","point_value":-0.0091159884},{"point_timestamp":"2020-09-17","point_value":0.0737491087},{"point_timestamp":"2020-09-18","point_value":0.1381691456},{"point_timestamp":"2020-09-19","point_value":-0.1136004924},{"point_timestamp":"2020-09-20","point_value":-0.0134964724},{"point_timestamp":"2020-09-21","point_value":-0.1350593794},{"point_timestamp":"2020-09-22","point_value":-0.020052718},{"point_timestamp":"2020-09-23","point_value":-0.0095054661},{"point_timestamp":"2020-09-24","point_value":0.0733596311},{"point_timestamp":"2020-09-25","point_value":0.1377796679},{"point_timestamp":"2020-09-26","point_value":-0.1139899701},{"point_timestamp":"2020-09-27","point_value":-0.0138859501},{"point_timestamp":"2020-09-28","point_value":-0.1354488571},{"point_timestamp":"2020-09-29","point_value":-0.0204421956},{"point_timestamp":"2020-09-30","point_value":-0.0098949437},{"point_timestamp":"2020-10-01","point_value":0.0729701534},{"point_timestamp":"2020-10-02","point_value":0.1373901903},{"point_timestamp":"2020-10-03","point_value":-0.1143794477},{"point_timestamp":"2020-10-04","point_value":-0.0142754277},{"point_timestamp":"2020-10-05","point_value":-0.1358383348},{"point_timestamp":"2020-10-06","point_value":-0.0208316733},{"point_timestamp":"2020-10-07","point_value":-0.0102844214},{"point_timestamp":"2020-10-08","point_value":0.0725806757},{"point_timestamp":"2020-10-09","point_value":0.1370007126},{"point_timestamp":"2020-10-10","point_value":-0.1147689254},{"point_timestamp":"2020-10-11","point_value":-0.0146649054},{"point_timestamp":"2020-10-12","point_value":-0.1362278124},{"point_timestamp":"2020-10-13","point_value":-0.021221151},{"point_timestamp":"2020-10-14","point_value":-0.0106738991},{"point_timestamp":"2020-10-15","point_value":0.0721911981},{"point_timestamp":"2020-10-16","point_value":0.136611235},{"point_timestamp":"2020-10-17","point_value":-0.115158403},{"point_timestamp":"2020-10-18","point_value":-0.015054383},{"point_timestamp":"2020-10-19","point_value":-0.1366172901},{"point_timestamp":"2020-10-20","point_value":-0.0216106286},{"point_timestamp":"2020-10-21","point_value":-0.0110633767},{"point_timestamp":"2020-10-22","point_value":0.0718017204},{"point_timestamp":"2020-10-23","point_value":0.1362217573},{"point_timestamp":"2020-10-24","point_value":-0.1155478807},{"point_timestamp":"2020-10-25","point_value":-0.0154438607},{"point_timestamp":"2020-10-26","point_value":-0.1370067677},{"point_timestamp":"2020-10-27","point_value":-0.0220001063},{"point_timestamp":"2020-10-28","point_value":-0.0114528544},{"point_timestamp":"2020-10-29","point_value":0.0714122428},{"point_timestamp":"2020-10-30","point_value":0.1358322797},{"point_timestamp":"2020-10-31","point_value":-0.1159373583},{"point_timestamp":"2020-11-01","point_value":-0.0158333384},{"point_timestamp":"2020-11-02","point_value":-0.1373962454},{"point_timestamp":"2020-11-03","point_value":-0.0223895839},{"point_timestamp":"2020-11-04","point_value":-0.011842332},{"point_timestamp":"2020-11-05","point_value":0.0710227651},{"point_timestamp":"2020-11-06","point_value":0.135442802},{"point_timestamp":"2020-11-07","point_value":-0.116326836},{"point_timestamp":"2020-11-08","point_value":-0.016222816},{"point_timestamp":"2020-11-09","point_value":-0.137785723},{"point_timestamp":"2020-11-10","point_value":-0.0227790616},{"point_timestamp":"2020-11-11","point_value":-0.0122318097},{"point_timestamp":"2020-11-12","point_value":0.0706332875},{"point_timestamp":"2020-11-13","point_value":0.1350533243},{"point_timestamp":"2020-11-14","point_value":-0.1167163137},{"point_timestamp":"2020-11-15","point_value":-0.0166122937},{"point_timestamp":"2020-11-16","point_value":-0.1381752007},{"point_timestamp":"2020-11-17","point_value":-0.0231685392},{"point_timestamp":"2020-11-18","point_value":-0.0126212873},{"point_timestamp":"2020-11-19","point_value":0.0702438098},{"point_timestamp":"2020-11-20","point_value":0.1346638467},{"point_timestamp":"2020-11-21","point_value":-0.1171057913},{"point_timestamp":"2020-11-22","point_value":-0.0170017713},{"point_timestamp":"2020-11-23","point_value":-0.1385646784},{"point_timestamp":"2020-11-24","point_value":-0.0235580169},{"point_timestamp":"2020-11-25","point_value":-0.013010765},{"point_timestamp":"2020-11-26","point_value":0.0698543321},{"point_timestamp":"2020-11-27","point_value":0.134274369},{"point_timestamp":"2020-11-28","point_value":-0.117495269},{"point_timestamp":"2020-11-29","point_value":-0.017391249},{"point_timestamp":"2020-11-30","point_value":-0.138954156},{"point_timestamp":"2020-12-01","point_value":-0.0239474945},{"point_timestamp":"2020-12-02","point_value":-0.0134002427},{"point_timestamp":"2020-12-03","point_value":0.0694648545},{"point_timestamp":"2020-12-04","point_value":0.1338848914},{"point_timestamp":"2020-12-05","point_value":-0.1178847466},{"point_timestamp":"2020-12-06","point_value":-0.0177807266},{"point_timestamp":"2020-12-07","point_value":-0.1393436337},{"point_timestamp":"2020-12-08","point_value":-0.0243369722},{"point_timestamp":"2020-12-09","point_value":-0.0137897203},{"point_timestamp":"2020-12-10","point_value":0.0690753768},{"point_timestamp":"2020-12-11","point_value":0.1334954137},{"point_timestamp":"2020-12-12","point_value":-0.1182742243},{"point_timestamp":"2020-12-13","point_value":-0.0181702043},{"point_timestamp":"2020-12-14","point_value":-0.1397331113},{"point_timestamp":"2020-12-15","point_value":-0.0247264499},{"point_timestamp":"2020-12-16","point_value":-0.014179198},{"point_timestamp":"2020-12-17","point_value":0.0686858992},{"point_timestamp":"2020-12-18","point_value":0.1331059361},{"point_timestamp":"2020-12-19","point_value":-0.1186637019},{"point_timestamp":"2020-12-20","point_value":-0.018559682},{"point_timestamp":"2020-12-21","point_value":-0.140122589},{"point_timestamp":"2020-12-22","point_value":-0.0251159275},{"point_timestamp":"2020-12-23","point_value":-0.0145686756},{"point_timestamp":"2020-12-24","point_value":0.0682964215},{"point_timestamp":"2020-12-25","point_value":0.1327164584},{"point_timestamp":"2020-12-26","point_value":-0.1190531796},{"point_timestamp":"2020-12-27","point_value":-0.0189491596},{"point_timestamp":"2020-12-28","point_value":-0.1405120666},{"point_timestamp":"2020-12-29","point_value":-0.0255054052},{"point_timestamp":"2020-12-30","point_value":-0.0149581533},{"point_timestamp":"2020-12-31","point_value":0.0679069439},{"point_timestamp":"2021-01-01","point_value":0.1323269807},{"point_timestamp":"2021-01-02","point_value":-0.1194426573},{"point_timestamp":"2021-01-03","point_value":-0.0193386373},{"point_timestamp":"2021-01-04","point_value":-0.1409015443},{"point_timestamp":"2021-01-05","point_value":-0.0258948828},{"point_timestamp":"2021-01-06","point_value":-0.0153476309},{"point_timestamp":"2021-01-07","point_value":0.0675174662},{"point_timestamp":"2021-01-08","point_value":0.1319375031},{"point_timestamp":"2021-01-09","point_value":-0.1198321349},{"point_timestamp":"2021-01-10","point_value":-0.0197281149},{"point_timestamp":"2021-01-11","point_value":-0.141291022},{"point_timestamp":"2021-01-12","point_value":-0.0262843605},{"point_timestamp":"2021-01-13","point_value":-0.0157371086},{"point_timestamp":"2021-01-14","point_value":0.0671279885},{"point_timestamp":"2021-01-15","point_value":0.1315480254},{"point_timestamp":"2021-01-16","point_value":-0.1202216126},{"point_timestamp":"2021-01-17","point_value":-0.0201175926},{"point_timestamp":"2021-01-18","point_value":-0.1416804996},{"point_timestamp":"2021-01-19","point_value":-0.0266738381},{"point_timestamp":"2021-01-20","point_value":-0.0161265863},{"point_timestamp":"2021-01-21","point_value":0.0667385109},{"point_timestamp":"2021-01-22","point_value":0.1311585478},{"point_timestamp":"2021-01-23","point_value":-0.1206110902},{"point_timestamp":"2021-01-24","point_value":-0.0205070702},{"point_timestamp":"2021-01-25","point_value":-0.1420699773},{"point_timestamp":"2021-01-26","point_value":-0.0270633158},{"point_timestamp":"2021-01-27","point_value":-0.0165160639},{"point_timestamp":"2021-01-28","point_value":0.0663490332},{"point_timestamp":"2021-01-29","point_value":0.1307690701},{"point_timestamp":"2021-01-30","point_value":-0.1210005679},{"point_timestamp":"2021-01-31","point_value":-0.0208965479},{"point_timestamp":"2021-02-01","point_value":-0.1424594549},{"point_timestamp":"2021-02-02","point_value":-0.0274527935},{"point_timestamp":"2021-02-03","point_value":-0.0169055416},{"point_timestamp":"2021-02-04","point_value":0.0659595556},{"point_timestamp":"2021-02-05","point_value":0.1303795925},{"point_timestamp":"2021-02-06","point_value":-0.1213900455},{"point_timestamp":"2021-02-07","point_value":-0.0212860256},{"point_timestamp":"2021-02-08","point_value":-0.1428489326},{"point_timestamp":"2021-02-09","point_value":-0.0278422711},{"point_timestamp":"2021-02-10","point_value":-0.0172950192},{"point_timestamp":"2021-02-11","point_value":0.0655700779},{"point_timestamp":"2021-02-12","point_value":0.1299901148},{"point_timestamp":"2021-02-13","point_value":-0.1217795232},{"point_timestamp":"2021-02-14","point_value":-0.0216755032},{"point_timestamp":"2021-02-15","point_value":-0.1432384102},{"point_timestamp":"2021-02-16","point_value":-0.0282317488},{"point_timestamp":"2021-02-17","point_value":-0.0176844969},{"point_timestamp":"2021-02-18","point_value":0.0651806003},{"point_timestamp":"2021-02-19","point_value":0.1296006371},{"point_timestamp":"2021-02-20","point_value":-0.1221690009},{"point_timestamp":"2021-02-21","point_value":-0.0220649809},{"point_timestamp":"2021-02-22","point_value":-0.1436278879},{"point_timestamp":"2021-02-23","point_value":-0.0286212264},{"point_timestamp":"2021-02-24","point_value":-0.0180739745},{"point_timestamp":"2021-02-25","point_value":0.0647911226},{"point_timestamp":"2021-02-26","point_value":0.1292111595},{"point_timestamp":"2021-02-27","point_value":-0.1225584785},{"point_timestamp":"2021-02-28","point_value":-0.0224544585},{"point_timestamp":"2021-03-01","point_value":-0.1440173655},{"point_timestamp":"2021-03-02","point_value":-0.0290107041},{"point_timestamp":"2021-03-03","point_value":-0.0184634522},{"point_timestamp":"2021-03-04","point_value":0.0644016449},{"point_timestamp":"2021-03-05","point_value":0.1288216818},{"point_timestamp":"2021-03-06","point_value":-0.1229479562},{"point_timestamp":"2021-03-07","point_value":-0.0228439362},{"point_timestamp":"2021-03-08","point_value":-0.1444068432},{"point_timestamp":"2021-03-09","point_value":-0.0294001817},{"point_timestamp":"2021-03-10","point_value":-0.0188529299},{"point_timestamp":"2021-03-11","point_value":0.0640121673},{"point_timestamp":"2021-03-12","point_value":0.1284322042},{"point_timestamp":"2021-03-13","point_value":-0.1233374338},{"point_timestamp":"2021-03-14","point_value":-0.0232334138},{"point_timestamp":"2021-03-15","point_value":-0.1447963209},{"point_timestamp":"2021-03-16","point_value":-0.0297896594},{"point_timestamp":"2021-03-17","point_value":-0.0192424075},{"point_timestamp":"2021-03-18","point_value":0.0636226896},{"point_timestamp":"2021-03-19","point_value":0.1280427265},{"point_timestamp":"2021-03-20","point_value":-0.1237269115},{"point_timestamp":"2021-03-21","point_value":-0.0236228915},{"point_timestamp":"2021-03-22","point_value":-0.1451857985},{"point_timestamp":"2021-03-23","point_value":-0.0301791371},{"point_timestamp":"2021-03-24","point_value":-0.0196318852},{"point_timestamp":"2021-03-25","point_value":0.063233212},{"point_timestamp":"2021-03-26","point_value":0.1276532489},{"point_timestamp":"2021-03-27","point_value":-0.1241163891},{"point_timestamp":"2021-03-28","point_value":-0.0240123692},{"point_timestamp":"2021-03-29","point_value":-0.1455752762},{"point_timestamp":"2021-03-30","point_value":-0.0305686147},{"point_timestamp":"2021-03-31","point_value":-0.0200213628},{"point_timestamp":"2021-04-01","point_value":0.0628437343},{"point_timestamp":"2021-04-02","point_value":0.1272637712},{"point_timestamp":"2021-04-03","point_value":-0.1245058668},{"point_timestamp":"2021-04-04","point_value":-0.0244018468},{"point_timestamp":"2021-04-05","point_value":-0.1459647538},{"point_timestamp":"2021-04-06","point_value":-0.0309580924},{"point_timestamp":"2021-04-07","point_value":-0.0204108405},{"point_timestamp":"2021-04-08","point_value":0.0624542567},{"point_timestamp":"2021-04-09","point_value":0.1268742936},{"point_timestamp":"2021-04-10","point_value":-0.1248953445},{"point_timestamp":"2021-04-11","point_value":-0.0247913245},{"point_timestamp":"2021-04-12","point_value":-0.1463542315},{"point_timestamp":"2021-04-13","point_value":-0.03134757},{"point_timestamp":"2021-04-14","point_value":-0.0208003181},{"point_timestamp":"2021-04-15","point_value":0.062064779},{"point_timestamp":"2021-04-16","point_value":0.1264848159},{"point_timestamp":"2021-04-17","point_value":-0.1252848221},{"point_timestamp":"2021-04-18","point_value":-0.0251808021},{"point_timestamp":"2021-04-19","point_value":-0.1467437091},{"point_timestamp":"2021-04-20","point_value":-0.0317370477},{"point_timestamp":"2021-04-21","point_value":-0.0211897958},{"point_timestamp":"2021-04-22","point_value":0.0616753013},{"point_timestamp":"2021-04-23","point_value":0.1260953382},{"point_timestamp":"2021-04-24","point_value":-0.1256742998},{"point_timestamp":"2021-04-25","point_value":-0.0255702798},{"point_timestamp":"2021-04-26","point_value":-0.1471331868},{"point_timestamp":"2021-04-27","point_value":-0.0321265253},{"point_timestamp":"2021-04-28","point_value":-0.0215792735},{"point_timestamp":"2021-04-29","point_value":0.0612858237},{"point_timestamp":"2021-04-30","point_value":0.1257058606},{"point_timestamp":"2021-05-01","point_value":-0.1260637774},{"point_timestamp":"2021-05-02","point_value":-0.0259597574},{"point_timestamp":"2021-05-03","point_value":-0.1475226645},{"point_timestamp":"2021-05-04","point_value":-0.032516003},{"point_timestamp":"2021-05-05","point_value":-0.0219687511},{"point_timestamp":"2021-05-06","point_value":0.060896346},{"point_timestamp":"2021-05-07","point_value":0.1253163829},{"point_timestamp":"2021-05-08","point_value":-0.1264532551},{"point_timestamp":"2021-05-09","point_value":-0.0263492351},{"point_timestamp":"2021-05-10","point_value":-0.1479121421},{"point_timestamp":"2021-05-11","point_value":-0.0329054807},{"point_timestamp":"2021-05-12","point_value":-0.0223582288},{"point_timestamp":"2021-05-13","point_value":0.0605068684},{"point_timestamp":"2021-05-14","point_value":0.1249269053}]