[{"point_timestamp":"2020-01-01","point_value":0.1842134179},{"point_timestamp":"2020-01-02","point_value":0.2182472276},{"point_timestamp":"2020-01-03","point_value":0.2665862461},{"point_timestamp":"2020-01-04","point_value":0.1913787191},{"point_timestamp":"2020-01-05","point_value":0.0767707287},{"point_timestamp":"2020-01-06","point_value":0.2504533441},{"point_timestamp":"2020-01-07","point_value":0.2395286425},{"point_timestamp":"2020-01-08","point_value":0.1883552917},{"point_timestamp":"2020-01-09","point_value":0.2223891014},{"point_timestamp":"2020-01-10","point_value":0.27072812},{"point_timestamp":"2020-01-11","point_value":0.1955205929},{"point_timestamp":"2020-01-12","point_value":0.0809126025},{"point_timestamp":"2020-01-13","point_value":0.2545952179},{"point_timestamp":"2020-01-14","point_value":0.2436705164},{"point_timestamp":"2020-01-15","point_value":0.1924971655},{"point_timestamp":"2020-01-16","point_value":0.2265309752},{"point_timestamp":"2020-01-17","point_value":0.2748699938},{"point_timestamp":"2020-01-18","point_value":0.1996624667},{"point_timestamp":"2020-01-19","point_value":0.0850544763},{"point_timestamp":"2020-01-20","point_value":0.2587370917},{"point_timestamp":"2020-01-21","point_value":0.2478123902},{"point_timestamp":"2020-01-22","point_value":0.1966390393},{"point_timestamp":"2020-01-23","point_value":0.2306728491},{"point_timestamp":"2020-01-24","point_value":0.2790118676},{"point_timestamp":"2020-01-25","point_value":0.2038043405},{"point_timestamp":"2020-01-26","point_value":0.0891963501},{"point_timestamp":"2020-01-27","point_value":0.2628789655},{"point_timestamp":"2020-01-28","point_value":0.251954264},{"point_timestamp":"2020-01-29","point_value":0.2007809132},{"point_timestamp":"2020-01-30","point_value":0.2348147229},{"point_timestamp":"2020-01-31","point_value":0.2831537415},{"point_timestamp":"2020-02-01","point_value":0.2079462144},{"point_timestamp":"2020-02-02","point_value":0.093338224},{"point_timestamp":"2020-02-03","point_value":0.2670208394},{"point_timestamp":"2020-02-04","point_value":0.2560961378},{"point_timestamp":"2020-02-05","point_value":0.204922787},{"point_timestamp":"2020-02-06","point_value":0.2389565967},{"point_timestamp":"2020-02-07","point_value":0.2872956153},{"point_timestamp":"2020-02-08","point_value":0.2120880882},{"point_timestamp":"2020-02-09","point_value":0.0974800978},{"point_timestamp":"2020-02-10","point_value":0.2711627132},{"point_timestamp":"2020-02-11","point_value":0.2602380117},{"point_timestamp":"2020-02-12","point_value":0.2090646608},{"point_timestamp":"2020-02-13","point_value":0.2430984705},{"point_timestamp":"2020-02-14","point_value":0.2914374891},{"point_timestamp":"2020-02-15","point_value":0.216229962},{"point_timestamp":"2020-02-16","point_value":0.1016219716},{"point_timestamp":"2020-02-17","point_value":0.275304587},{"point_timestamp":"2020-02-18","point_value":0.2643798855},{"point_timestamp":"2020-02-19","point_value":0.2132065347},{"point_timestamp":"2020-02-20","point_value":0.2472403444},{"point_timestamp":"2020-02-21","point_value":0.2955793629},{"point_timestamp":"2020-02-22","point_value":0.2203718359},{"point_timestamp":"2020-02-23","point_value":0.1057638455},{"point_timestamp":"2020-02-24","point_value":0.2794464609},{"point_timestamp":"2020-02-25","point_value":0.2685217593},{"point_timestamp":"2020-02-26","point_value":0.2173484085},{"point_timestamp":"2020-02-27","point_value":0.2513822182},{"point_timestamp":"2020-02-28","point_value":0.2997212368},{"point_timestamp":"2020-02-29","point_value":0.2245137097},{"point_timestamp":"2020-03-01","point_value":0.1099057193},{"point_timestamp":"2020-03-02","point_value":0.2835883347},{"point_timestamp":"2020-03-03","point_value":0.2726636332},{"point_timestamp":"2020-03-04","point_value":0.2214902823},{"point_timestamp":"2020-03-05","point_value":0.255524092},{"point_timestamp":"2020-03-06","point_value":0.3038631106},{"point_timestamp":"2020-03-07","point_value":0.2286555835},{"point_timestamp":"2020-03-08","point_value":0.1140475931},{"point_timestamp":"2020-03-09","point_value":0.2877302085},{"point_timestamp":"2020-03-10","point_value":0.276805507},{"point_timestamp":"2020-03-11","point_value":0.2256321562},{"point_timestamp":"2020-03-12","point_value":0.2596659659},{"point_timestamp":"2020-03-13","point_value":0.3080049844},{"point_timestamp":"2020-03-14","point_value":0.2327974574},{"point_timestamp":"2020-03-15","point_value":0.118189467},{"point_timestamp":"2020-03-16","point_value":0.2918720824},{"point_timestamp":"2020-03-17","point_value":0.2809473808},{"point_timestamp":"2020-03-18","point_value":0.22977403},{"point_timestamp":"2020-03-19","point_value":0.2638078397},{"point_timestamp":"2020-03-20","point_value":0.3121468583},{"point_timestamp":"2020-03-21","point_value":0.2369393312},{"point_timestamp":"2020-03-22","point_value":0.1223313408},{"point_timestamp":"2020-03-23","point_value":0.2960139562},{"point_timestamp":"2020-03-24","point_value":0.2850892547},{"point_timestamp":"2020-03-25","point_value":0.2339159038},{"point_timestamp":"2020-03-26","point_value":0.2679497135},{"point_timestamp":"2020-03-27","point_value":0.3162887321},{"point_timestamp":"2020-03-28","point_value":0.241081205},{"point_timestamp":"2020-03-29","point_value":0.1264732146},{"point_timestamp":"2020-03-30","point_value":0.30015583},{"point_timestamp":"2020-03-31","point_value":0.2892311285},{"point_timestamp":"2020-04-01","point_value":0.2380577777},{"point_timestamp":"2020-04-02","point_value":0.2720915874},{"point_timestamp":"2020-04-03","point_value":0.3204306059},{"point_timestamp":"2020-04-04","point_value":0.2452230788},{"point_timestamp":"2020-04-05","point_value":0.1306150884},{"point_timestamp":"2020-04-06","point_value":0.3042977038},{"point_timestamp":"2020-04-07","point_value":0.2933730023},{"point_timestamp":"2020-04-08","point_value":0.2421996515},{"point_timestamp":"2020-04-09","point_value":0.2762334612},{"point_timestamp":"2020-04-10","point_value":0.3245724798},{"point_timestamp":"2020-04-11","point_value":0.2493649527},{"point_timestamp":"2020-04-12","point_value":0.1347569623},{"point_timestamp":"2020-04-13","point_value":0.3084395777},{"point_timestamp":"2020-04-14","point_value":0.2975148762},{"point_timestamp":"2020-04-15","point_value":0.2463415253},{"point_timestamp":"2020-04-16","point_value":0.280375335},{"point_timestamp":"2020-04-17","point_value":0.3287143536},{"point_timestamp":"2020-04-18","point_value":0.2535068265},{"point_timestamp":"2020-04-19","point_value":0.1388988361},{"point_timestamp":"2020-04-20","point_value":0.3125814515},{"point_timestamp":"2020-04-21","point_value":0.30165675},{"point_timestamp":"2020-04-22","point_value":0.2504833991},{"point_timestamp":"2020-04-23","point_value":0.2845172089},{"point_timestamp":"2020-04-24","point_value":0.3328562274},{"point_timestamp":"2020-04-25","point_value":0.2576487003},{"point_timestamp":"2020-04-26","point_value":0.1430407099},{"point_timestamp":"2020-04-27","point_value":0.3167233253},{"point_timestamp":"2020-04-28","point_value":0.3057986238},{"point_timestamp":"2020-04-29","point_value":0.254625273},{"point_timestamp":"2020-04-30","point_value":0.2886590827},{"point_timestamp":"2020-05-01","point_value":0.3369981012},{"point_timestamp":"2020-05-02","point_value":0.2617905742},{"point_timestamp":"2020-05-03","point_value":0.1471825838},{"point_timestamp":"2020-05-04","point_value":0.3208651992},{"point_timestamp":"2020-05-05","point_value":0.3099404976},{"point_timestamp":"2020-05-06","point_value":0.2587671468},{"point_timestamp":"2020-05-07","point_value":0.2928009565},{"point_timestamp":"2020-05-08","point_value":0.3411399751},{"point_timestamp":"2020-05-09","point_value":0.265932448},{"point_timestamp":"2020-05-10","point_value":0.1513244576},{"point_timestamp":"2020-05-11","point_value":0.325007073},{"point_timestamp":"2020-05-12","point_value":0.3140823715},{"point_timestamp":"2020-05-13","point_value":0.2629090206},{"point_timestamp":"2020-05-14","point_value":0.2969428303},{"point_timestamp":"2020-05-15","point_value":0.3452818489},{"point_timestamp":"2020-05-16","point_value":0.2700743218},{"point_timestamp":"2020-05-17","point_value":0.1554663314},{"point_timestamp":"2020-05-18","point_value":0.3291489468},{"point_timestamp":"2020-05-19","point_value":0.3182242453},{"point_timestamp":"2020-05-20","point_value":0.2670508945},{"point_timestamp":"2020-05-21","point_value":0.3010847042},{"point_timestamp":"2020-05-22","point_value":0.3494237227},{"point_timestamp":"2020-05-23","point_value":0.2742161957},{"point_timestamp":"2020-05-24","point_value":0.1596082053},{"point_timestamp":"2020-05-25","point_value":0.3332908207},{"point_timestamp":"2020-05-26","point_value":0.3223661191},{"point_timestamp":"2020-05-27","point_value":0.2711927683},{"point_timestamp":"2020-05-28","point_value":0.305226578},{"point_timestamp":"2020-05-29","point_value":0.3535655966},{"point_timestamp":"2020-05-30","point_value":0.2783580695},{"point_timestamp":"2020-05-31","point_value":0.1637500791},{"point_timestamp":"2020-06-01","point_value":0.3374326945},{"point_timestamp":"2020-06-02","point_value":0.326507993},{"point_timestamp":"2020-06-03","point_value":0.2753346421},{"point_timestamp":"2020-06-04","point_value":0.3093684518},{"point_timestamp":"2020-06-05","point_value":0.3577074704},{"point_timestamp":"2020-06-06","point_value":0.2824999433},{"point_timestamp":"2020-06-07","point_value":0.1678919529},{"point_timestamp":"2020-06-08","point_value":0.3415745683},{"point_timestamp":"2020-06-09","point_value":0.3306498668},{"point_timestamp":"2020-06-10","point_value":0.279476516},{"point_timestamp":"2020-06-11","point_value":0.3135103257},{"point_timestamp":"2020-06-12","point_value":0.3618493442},{"point_timestamp":"2020-06-13","point_value":0.2866418171},{"point_timestamp":"2020-06-14","point_value":0.1720338267},{"point_timestamp":"2020-06-15","point_value":0.3457164421},{"point_timestamp":"2020-06-16","point_value":0.3347917406},{"point_timestamp":"2020-06-17","point_value":0.2836183898},{"point_timestamp":"2020-06-18","point_value":0.3176521995},{"point_timestamp":"2020-06-19","point_value":0.3659912181},{"point_timestamp":"2020-06-20","point_value":0.290783691},{"point_timestamp":"2020-06-21","point_value":0.1761757006},{"point_timestamp":"2020-06-22","point_value":0.349858316},{"point_timestamp":"2020-06-23","point_value":0.3389336145},{"point_timestamp":"2020-06-24","point_value":0.2877602636},{"point_timestamp":"2020-06-25","point_value":0.3217940733},{"point_timestamp":"2020-06-26","point_value":0.3701330919},{"point_timestamp":"2020-06-27","point_value":0.2949255648},{"point_timestamp":"2020-06-28","point_value":0.1803175744},{"point_timestamp":"2020-06-29","point_value":0.3540001898},{"point_timestamp":"2020-06-30","point_value":0.3430754883},{"point_timestamp":"2020-07-01","point_value":0.2919021374},{"point_timestamp":"2020-07-02","point_value":0.3259359472},{"point_timestamp":"2020-07-03","point_value":0.3742749657},{"point_timestamp":"2020-07-04","point_value":0.2990674386},{"point_timestamp":"2020-07-05","point_value":0.1844594482},{"point_timestamp":"2020-07-06","point_value":0.3581420636},{"point_timestamp":"2020-07-07","point_value":0.3472173621},{"point_timestamp":"2020-07-08","point_value":0.2960440113},{"point_timestamp":"2020-07-09","point_value":0.330077821},{"point_timestamp":"2020-07-10","point_value":0.3784168396},{"point_timestamp":"2020-07-11","point_value":0.3032093125},{"point_timestamp":"2020-07-12","point_value":0.1886013221},{"point_timestamp":"2020-07-13","point_value":0.3622839375},{"point_timestamp":"2020-07-14","point_value":0.3513592359},{"point_timestamp":"2020-07-15","point_value":0.3001858851},{"point_timestamp":"2020-07-16","point_value":0.3342196948},{"point_timestamp":"2020-07-17","point_value":0.3825587134},{"point_timestamp":"2020-07-18","point_value":0.3073511863},{"point_timestamp":"2020-07-19","point_value":0.1927431959},{"point_timestamp":"2020-07-20","point_value":0.3664258113},{"point_timestamp":"2020-07-21","point_value":0.3555011098},{"point_timestamp":"2020-07-22","point_value":0.3043277589},{"point_timestamp":"2020-07-23","point_value":0.3383615686},{"point_timestamp":"2020-07-24","point_value":0.3867005872},{"point_timestamp":"2020-07-25","point_value":0.3114930601},{"point_timestamp":"2020-07-26","point_value":0.1968850697},{"point_timestamp":"2020-07-27","point_value":0.3705676851},{"point_timestamp":"2020-07-28","point_value":0.3596429836},{"point_timestamp":"2020-07-29","point_value":0.3084696328},{"point_timestamp":"2020-07-30","point_value":0.3425034425},{"point_timestamp":"2020-07-31","point_value":0.390842461},{"point_timestamp":"2020-08-01","point_value":0.315634934},{"point_timestamp":"2020-08-02","point_value":0.2010269436},{"point_timestamp":"2020-08-03","point_value":0.374709559},{"point_timestamp":"2020-08-04","point_value":0.3637848574},{"point_timestamp":"2020-08-05","point_value":0.3126115066},{"point_timestamp":"2020-08-06","point_value":0.3466453163},{"point_timestamp":"2020-08-07","point_value":0.3949843349},{"point_timestamp":"2020-08-08","point_value":0.3197768078},{"point_timestamp":"2020-08-09","point_value":0.2051688174},{"point_timestamp":"2020-08-10","point_value":0.3788514328},{"point_timestamp":"2020-08-11","point_value":0.3679267313},{"point_timestamp":"2020-08-12","point_value":0.3167533804},{"point_timestamp":"2020-08-13","point_value":0.3507871901},{"point_timestamp":"2020-08-14","point_value":0.3991262087},{"point_timestamp":"2020-08-15","point_value":0.3239186816},{"point_timestamp":"2020-08-16","point_value":0.2093106912},{"point_timestamp":"2020-08-17","point_value":0.3829933066},{"point_timestamp":"2020-08-18","point_value":0.3720686051},{"point_timestamp":"2020-08-19","point_value":0.3208952543},{"point_timestamp":"2020-08-20","point_value":0.354929064},{"point_timestamp":"2020-08-21","point_value":0.4032680825},{"point_timestamp":"2020-08-22","point_value":0.3280605555},{"point_timestamp":"2020-08-23","point_value":0.2134525651},{"point_timestamp":"2020-08-24","point_value":0.3871351805},{"point_timestamp":"2020-08-25","point_value":0.3762104789},{"point_timestamp":"2020-08-26","point_value":0.3250371281},{"point_timestamp":"2020-08-27","point_value":0.3590709378},{"point_timestamp":"2020-08-28","point_value":0.4074099564},{"point_timestamp":"2020-08-29","point_value":0.3322024293},{"point_timestamp":"2020-08-30","point_value":0.2175944389},{"point_timestamp":"2020-08-31","point_value":0.3912770543},{"point_timestamp":"2020-09-01","point_value":0.3803523528},{"point_timestamp":"2020-09-02","point_value":0.3291790019},{"point_timestamp":"2020-09-03","point_value":0.3632128116},{"point_timestamp":"2020-09-04","point_value":0.4115518302},{"point_timestamp":"2020-09-05","point_value":0.3363443031},{"point_timestamp":"2020-09-06","point_value":0.2217363127},{"point_timestamp":"2020-09-07","point_value":0.3954189281},{"point_timestamp":"2020-09-08","point_value":0.3844942266},{"point_timestamp":"2020-09-09","point_value":0.3333208757},{"point_timestamp":"2020-09-10","point_value":0.3673546855},{"point_timestamp":"2020-09-11","point_value":0.415693704},{"point_timestamp":"2020-09-12","point_value":0.3404861769},{"point_timestamp":"2020-09-13","point_value":0.2258781865},{"point_timestamp":"2020-09-14","point_value":0.3995608019},{"point_timestamp":"2020-09-15","point_value":0.3886361004},{"point_timestamp":"2020-09-16","point_value":0.3374627496},{"point_timestamp":"2020-09-17","point_value":0.3714965593},{"point_timestamp":"2020-09-18","point_value":0.4198355779},{"point_timestamp":"2020-09-19","point_value":0.3446280508},{"point_timestamp":"2020-09-20","point_value":0.2300200604},{"point_timestamp":"2020-09-21","point_value":0.4037026758},{"point_timestamp":"2020-09-22","point_value":0.3927779742},{"point_timestamp":"2020-09-23","point_value":0.3416046234},{"point_timestamp":"2020-09-24","point_value":0.3756384331},{"point_timestamp":"2020-09-25","point_value":0.4239774517},{"point_timestamp":"2020-09-26","point_value":0.3487699246},{"point_timestamp":"2020-09-27","point_value":0.2341619342},{"point_timestamp":"2020-09-28","point_value":0.4078445496},{"point_timestamp":"2020-09-29","point_value":0.3969198481},{"point_timestamp":"2020-09-30","point_value":0.3457464972},{"point_timestamp":"2020-10-01","point_value":0.3797803069},{"point_timestamp":"2020-10-02","point_value":0.4281193255},{"point_timestamp":"2020-10-03","point_value":0.3529117984},{"point_timestamp":"2020-10-04","point_value":0.238303808},{"point_timestamp":"2020-10-05","point_value":0.4119864234},{"point_timestamp":"2020-10-06","point_value":0.4010617219},{"point_timestamp":"2020-10-07","point_value":0.3498883711},{"point_timestamp":"2020-10-08","point_value":0.3839221808},{"point_timestamp":"2020-10-09","point_value":0.4322611993},{"point_timestamp":"2020-10-10","point_value":0.3570536723},{"point_timestamp":"2020-10-11","point_value":0.2424456819},{"point_timestamp":"2020-10-12","point_value":0.4161282973},{"point_timestamp":"2020-10-13","point_value":0.4052035957},{"point_timestamp":"2020-10-14","point_value":0.3540302449},{"point_timestamp":"2020-10-15","point_value":0.3880640546},{"point_timestamp":"2020-10-16","point_value":0.4364030732},{"point_timestamp":"2020-10-17","point_value":0.3611955461},{"point_timestamp":"2020-10-18","point_value":0.2465875557},{"point_timestamp":"2020-10-19","point_value":0.4202701711},{"point_timestamp":"2020-10-20","point_value":0.4093454696},{"point_timestamp":"2020-10-21","point_value":0.3581721187},{"point_timestamp":"2020-10-22","point_value":0.3922059284},{"point_timestamp":"2020-10-23","point_value":0.440544947},{"point_timestamp":"2020-10-24","point_value":0.3653374199},{"point_timestamp":"2020-10-25","point_value":0.2507294295},{"point_timestamp":"2020-10-26","point_value":0.4244120449},{"point_timestamp":"2020-10-27","point_value":0.4134873434},{"point_timestamp":"2020-10-28","point_value":0.3623139926},{"point_timestamp":"2020-10-29","point_value":0.3963478023},{"point_timestamp":"2020-10-30","point_value":0.4446868208},{"point_timestamp":"2020-10-31","point_value":0.3694792938},{"point_timestamp":"2020-11-01","point_value":0.2548713034},{"point_timestamp":"2020-11-02","point_value":0.4285539188},{"point_timestamp":"2020-11-03","point_value":0.4176292172},{"point_timestamp":"2020-11-04","point_value":0.3664558664},{"point_timestamp":"2020-11-05","point_value":0.4004896761},{"point_timestamp":"2020-11-06","point_value":0.4488286947},{"point_timestamp":"2020-11-07","point_value":0.3736211676},{"point_timestamp":"2020-11-08","point_value":0.2590131772},{"point_timestamp":"2020-11-09","point_value":0.4326957926},{"point_timestamp":"2020-11-10","point_value":0.4217710911},{"point_timestamp":"2020-11-11","point_value":0.3705977402},{"point_timestamp":"2020-11-12","point_value":0.4046315499},{"point_timestamp":"2020-11-13","point_value":0.4529705685},{"point_timestamp":"2020-11-14","point_value":0.3777630414},{"point_timestamp":"2020-11-15","point_value":0.263155051},{"point_timestamp":"2020-11-16","point_value":0.4368376664},{"point_timestamp":"2020-11-17","point_value":0.4259129649},{"point_timestamp":"2020-11-18","point_value":0.3747396141},{"point_timestamp":"2020-11-19","point_value":0.4087734238},{"point_timestamp":"2020-11-20","point_value":0.4571124423},{"point_timestamp":"2020-11-21","point_value":0.3819049152},{"point_timestamp":"2020-11-22","point_value":0.2672969248},{"point_timestamp":"2020-11-23","point_value":0.4409795402},{"point_timestamp":"2020-11-24","point_value":0.4300548387},{"point_timestamp":"2020-11-25","point_value":0.3788814879},{"point_timestamp":"2020-11-26","point_value":0.4129152976},{"point_timestamp":"2020-11-27","point_value":0.4612543162},{"point_timestamp":"2020-11-28","point_value":0.3860467891},{"point_timestamp":"2020-11-29","point_value":0.2714387987},{"point_timestamp":"2020-11-30","point_value":0.4451214141},{"point_timestamp":"2020-12-01","point_value":0.4341967126},{"point_timestamp":"2020-12-02","point_value":0.3830233617},{"point_timestamp":"2020-12-03","point_value":0.4170571714},{"point_timestamp":"2020-12-04","point_value":0.46539619},{"point_timestamp":"2020-12-05","point_value":0.3901886629},{"point_timestamp":"2020-12-06","point_value":0.2755806725},{"point_timestamp":"2020-12-07","point_value":0.4492632879},{"point_timestamp":"2020-12-08","point_value":0.4383385864},{"point_timestamp":"2020-12-09","point_value":0.3871652355},{"point_timestamp":"2020-12-10","point_value":0.4211990453},{"point_timestamp":"2020-12-11","point_value":0.4695380638},{"point_timestamp":"2020-12-12","point_value":0.3943305367},{"point_timestamp":"2020-12-13","point_value":0.2797225463},{"point_timestamp":"2020-12-14","point_value":0.4534051617},{"point_timestamp":"2020-12-15","point_value":0.4424804602},{"point_timestamp":"2020-12-16","point_value":0.3913071094},{"point_timestamp":"2020-12-17","point_value":0.4253409191},{"point_timestamp":"2020-12-18","point_value":0.4736799376},{"point_timestamp":"2020-12-19","point_value":0.3984724106},{"point_timestamp":"2020-12-20","point_value":0.2838644202},{"point_timestamp":"2020-12-21","point_value":0.4575470356},{"point_timestamp":"2020-12-22","point_value":0.446622334},{"point_timestamp":"2020-12-23","point_value":0.3954489832},{"point_timestamp":"2020-12-24","point_value":0.4294827929},{"point_timestamp":"2020-12-25","point_value":0.4778218115},{"point_timestamp":"2020-12-26","point_value":0.4026142844},{"point_timestamp":"2020-12-27","point_value":0.288006294},{"point_timestamp":"2020-12-28","point_value":0.4616889094},{"point_timestamp":"2020-12-29","point_value":0.4507642079},{"point_timestamp":"2020-12-30","point_value":0.399590857},{"point_timestamp":"2020-12-31","point_value":0.4336246667},{"point_timestamp":"2021-01-01","point_value":0.4819636853},{"point_timestamp":"2021-01-02","point_value":0.4067561582},{"point_timestamp":"2021-01-03","point_value":0.2921481678},{"point_timestamp":"2021-01-04","point_value":0.4658307832},{"point_timestamp":"2021-01-05","point_value":0.4549060817},{"point_timestamp":"2021-01-06","point_value":0.4037327309},{"point_timestamp":"2021-01-07","point_value":0.4377665406},{"point_timestamp":"2021-01-08","point_value":0.4861055591},{"point_timestamp":"2021-01-09","point_value":0.4108980321},{"point_timestamp":"2021-01-10","point_value":0.2962900417},{"point_timestamp":"2021-01-11","point_value":0.4699726571},{"point_timestamp":"2021-01-12","point_value":0.4590479555},{"point_timestamp":"2021-01-13","point_value":0.4078746047},{"point_timestamp":"2021-01-14","point_value":0.4419084144},{"point_timestamp":"2021-01-15","point_value":0.490247433},{"point_timestamp":"2021-01-16","point_value":0.4150399059},{"point_timestamp":"2021-01-17","point_value":0.3004319155},{"point_timestamp":"2021-01-18","point_value":0.4741145309},{"point_timestamp":"2021-01-19","point_value":0.4631898294},{"point_timestamp":"2021-01-20","point_value":0.4120164785},{"point_timestamp":"2021-01-21","point_value":0.4460502882},{"point_timestamp":"2021-01-22","point_value":0.4943893068},{"point_timestamp":"2021-01-23","point_value":0.4191817797},{"point_timestamp":"2021-01-24","point_value":0.3045737893},{"point_timestamp":"2021-01-25","point_value":0.4782564047},{"point_timestamp":"2021-01-26","point_value":0.4673317032},{"point_timestamp":"2021-01-27","point_value":0.4161583524},{"point_timestamp":"2021-01-28","point_value":0.4501921621},{"point_timestamp":"2021-01-29","point_value":0.4985311806},{"point_timestamp":"2021-01-30","point_value":0.4233236535},{"point_timestamp":"2021-01-31","point_value":0.3087156631},{"point_timestamp":"2021-02-01","point_value":0.4823982785},{"point_timestamp":"2021-02-02","point_value":0.471473577},{"point_timestamp":"2021-02-03","point_value":0.4203002262},{"point_timestamp":"2021-02-04","point_value":0.4543340359},{"point_timestamp":"2021-02-05","point_value":0.5026730545},{"point_timestamp":"2021-02-06","point_value":0.4274655274},{"point_timestamp":"2021-02-07","point_value":0.312857537},{"point_timestamp":"2021-02-08","point_value":0.4865401524},{"point_timestamp":"2021-02-09","point_value":0.4756154509},{"point_timestamp":"2021-02-10","point_value":0.4244421},{"point_timestamp":"2021-02-11","point_value":0.4584759097},{"point_timestamp":"2021-02-12","point_value":0.5068149283},{"point_timestamp":"2021-02-13","point_value":0.4316074012},{"point_timestamp":"2021-02-14","point_value":0.3169994108},{"point_timestamp":"2021-02-15","point_value":0.4906820262},{"point_timestamp":"2021-02-16","point_value":0.4797573247},{"point_timestamp":"2021-02-17","point_value":0.4285839738},{"point_timestamp":"2021-02-18","point_value":0.4626177836},{"point_timestamp":"2021-02-19","point_value":0.5109568021},{"point_timestamp":"2021-02-20","point_value":0.435749275},{"point_timestamp":"2021-02-21","point_value":0.3211412846},{"point_timestamp":"2021-02-22","point_value":0.4948239},{"point_timestamp":"2021-02-23","point_value":0.4838991985},{"point_timestamp":"2021-02-24","point_value":0.4327258477},{"point_timestamp":"2021-02-25","point_value":0.4667596574},{"point_timestamp":"2021-02-26","point_value":0.515098676},{"point_timestamp":"2021-02-27","point_value":0.4398911489},{"point_timestamp":"2021-02-28","point_value":0.3252831585},{"point_timestamp":"2021-03-01","point_value":0.4989657739},{"point_timestamp":"2021-03-02","point_value":0.4880410723},{"point_timestamp":"2021-03-03","point_value":0.4368677215},{"point_timestamp":"2021-03-04","point_value":0.4709015312},{"point_timestamp":"2021-03-05","point_value":0.5192405498},{"point_timestamp":"2021-03-06","point_value":0.4440330227},{"point_timestamp":"2021-03-07","point_value":0.3294250323},{"point_timestamp":"2021-03-08","point_value":0.5031076477},{"point_timestamp":"2021-03-09","point_value":0.4921829462},{"point_timestamp":"2021-03-10","point_value":0.4410095953},{"point_timestamp":"2021-03-11","point_value":0.475043405},{"point_timestamp":"2021-03-12","point_value":0.5233824236},{"point_timestamp":"2021-03-13","point_value":0.4481748965},{"point_timestamp":"2021-03-14","point_value":0.3335669061},{"point_timestamp":"2021-03-15","point_value":0.5072495215},{"point_timestamp":"2021-03-16","point_value":0.49632482},{"point_timestamp":"2021-03-17","point_value":0.4451514692},{"point_timestamp":"2021-03-18","point_value":0.4791852789},{"point_timestamp":"2021-03-19","point_value":0.5275242974},{"point_timestamp":"2021-03-20","point_value":0.4523167704},{"point_timestamp":"2021-03-21","point_value":0.33770878},{"point_timestamp":"2021-03-22","point_value":0.5113913954},{"point_timestamp":"2021-03-23","point_value":0.5004666938},{"point_timestamp":"2021-03-24","point_value":0.449293343},{"point_timestamp":"2021-03-25","point_value":0.4833271527},{"point_timestamp":"2021-03-26","point_value":0.5316661713},{"point_timestamp":"2021-03-27","point_value":0.4564586442},{"point_timestamp":"2021-03-28","point_value":0.3418506538},{"point_timestamp":"2021-03-29","point_value":0.5155332692},{"point_timestamp":"2021-03-30","point_value":0.5046085677},{"point_timestamp":"2021-03-31","point_value":0.4534352168},{"point_timestamp":"2021-04-01","point_value":0.4874690265},{"point_timestamp":"2021-04-02","point_value":0.5358080451},{"point_timestamp":"2021-04-03","point_value":0.460600518},{"point_timestamp":"2021-04-04","point_value":0.3459925276},{"point_timestamp":"2021-04-05","point_value":0.519675143},{"point_timestamp":"2021-04-06","point_value":0.5087504415},{"point_timestamp":"2021-04-07","point_value":0.4575770907},{"point_timestamp":"2021-04-08","point_value":0.4916109004},{"point_timestamp":"2021-04-09","point_value":0.5399499189},{"point_timestamp":"2021-04-10","point_value":0.4647423919},{"point_timestamp":"2021-04-11","point_value":0.3501344015},{"point_timestamp":"2021-04-12","point_value":0.5238170169},{"point_timestamp":"2021-04-13","point_value":0.5128923153},{"point_timestamp":"2021-04-14","point_value":0.4617189645},{"point_timestamp":"2021-04-15","point_value":0.4957527742},{"point_timestamp":"2021-04-16","point_value":0.5440917928},{"point_timestamp":"2021-04-17","point_value":0.4688842657},{"point_timestamp":"2021-04-18","point_value":0.3542762753},{"point_timestamp":"2021-04-19","point_value":0.5279588907},{"point_timestamp":"2021-04-20","point_value":0.5170341892},{"point_timestamp":"2021-04-21","point_value":0.4658608383},{"point_timestamp":"2021-04-22","point_value":0.499894648},{"point_timestamp":"2021-04-23","point_value":0.5482336666},{"point_timestamp":"2021-04-24","point_value":0.4730261395},{"point_timestamp":"2021-04-25","point_value":0.3584181491},{"point_timestamp":"2021-04-26","point_value":0.5321007645},{"point_timestamp":"2021-04-27","point_value":0.521176063},{"point_timestamp":"2021-04-28","point_value":0.4700027121},{"point_timestamp":"2021-04-29","point_value":0.5040365219},{"point_timestamp":"2021-04-30","point_value":0.5523755404},{"point_timestamp":"2021-05-01","point_value":0.4771680133},{"point_timestamp":"2021-05-02","point_value":0.3625600229},{"point_timestamp":"2021-05-03","point_value":0.5362426383},{"point_timestamp":"2021-05-04","point_value":0.5253179368},{"point_timestamp":"2021-05-05","point_value":0.474144586},{"point_timestamp":"2021-05-06","point_value":0.5081783957},{"point_timestamp":"2021-05-07","point_value":0.5565174143},{"point_timestamp":"2021-05-08","point_value":0.4813098872},{"point_timestamp":"2021-05-09","point_value":0.3667018968},{"point_timestamp":"2021-05-10","point_value":0.5403845122},{"point_timestamp":"2021-05-11","point_value":0.5294598106},{"point_timestamp":"2021-05-12","point_value":0.4782864598},{"point_timestamp":"2021-05-13","point_value":0.5123202695},{"point_timestamp":"2021-05-14","point_value":0.5606592881}]